{"data":[{"id":"94210","character_id":"62","prodid":"62065","subid":"2","info_1":"BSC19-001","info_2":"デストロイア（幼体）","info_3":"スピリット","info_4":"赤","info_5":"1","info_6":"赤1","info_7":"1","info_8":"1000","info_9":"2","info_10":"2000","info_11":null,"info_12":"-","info_13":"C","info_14":"[デストロイア（幼体）]はデッキに何枚でも入れることができる。<br />［Lv1-Lv2］『自分のメインステップ』<br />カード名に「デストロイア」と入っている自分のスピリット4体を破壊することで、自分の手札にあるカード名に「デストロイア」と入っているスピリットカード1枚を、コストを支払わずに召喚する。","info_15":null,"info_16":null,"info_17":"デストロイア(クロール体)から進化した姿。<br />口から放つ高濃度のミクロオキシゲンで攻撃をする。<br />集合合体を繰り返し成長を続ける。<br />－ゴジラvsデストロイア（1995）－","info_18":null,"info_19":null,"info_20":null,"info_21":"ようたい","info_22":"ようたい なんまい い<br />じぶん<br />めい はい じぶん たい はかい じぶん てふだ めい はい まい しはら しょうかん","info_23":null,"info_24":null,"info_25":"爬獣","info_26":"はじゅう","info_27":"BSC19-001","info_28":"BSC19-001","info_29":null,"info_30":"-","info_31":null,"info_32":null,"info_33":null,"info_34":"-","info_35":null,"info_36":null,"info_37":null,"info_38":null,"info_39":null,"info_40":null,"info_41":"戴斯特洛伊亞(幼體)","info_42":"[デストロイア（幼体）]可以不限數量地放進牌組。<br />LV1・LV2「自己的主要階段」只要破壞自己4張卡名中包含「デストロイア」的靈魂卡，自己手牌中1張卡名中包含「デストロイア」的靈魂卡，無需支付需求召喚到場中。\n","info_43":null,"info_44":null,"info_45":null,"info_46":null,"info_47":null,"info_48":null,"info_49":null,"info_50":null,"delflg":"0","created":"2015-03-11 15:50:53","modified":"2015-03-11 15:50:53","rank":"94210","freewords":"BSC19-001 デストロイア（幼体） スピリット 赤 [デストロイア（幼体）]はデッキに何枚でも入れることができる。<br />［Lv1-Lv2］『自分のメインステップ』<br />カード名に「デストロイア」と入っている自分のスピリット4体を破壊することで、自分の手札にあるカード名に「デストロイア」と入っているスピリットカード1枚を、コストを支払わずに召喚する。   ようたい ようたい なんまい い<br />じぶん<br />めい はい じぶん たい はかい じぶん てふだ めい はい まい しはら しょうかん   爬獣 はじゅう  ","cost_icon":"<img src='../image/card_serch/icon_red.gif' />","faq":"BSC19-001"},{"id":"94211","character_id":"62","prodid":"62065","subid":"2","info_1":"BSC19-002","info_2":"エビラ［2004］","info_3":"スピリット","info_4":"赤","info_5":"2","info_6":"赤1","info_7":"1","info_8":"2000","info_9":"3","info_10":"3000","info_11":null,"info_12":"-","info_13":"R","info_14":"［Lv1-Lv2］『このスピリットのアタック時』<br />このスピリットをBP+3000する。","info_15":"［Lv2］『このスピリットのアタック時』<br />自分はデッキから1枚ドローする。","info_16":null,"info_17":"大きなハサミを振り回して攻撃をする大えび怪獣。<br />M機関のミュータント兵に撃退される。<br />－ゴジラ FINALWARS（2004）－","info_18":null,"info_19":null,"info_20":null,"info_21":null,"info_22":"じ","info_23":"じ<br />じぶん まい","info_24":null,"info_25":"溶魚","info_26":"ようぎょ","info_27":"BSC19-002","info_28":"BSC19-002","info_29":null,"info_30":"-","info_31":null,"info_32":null,"info_33":null,"info_34":"-","info_35":null,"info_36":null,"info_37":null,"info_38":null,"info_39":null,"info_40":null,"info_41":"伊比拉[2004]","info_42":"LV1・LV2「這張靈魂卡攻擊時」這張靈魂卡 +3000BP。<br />LV2「這張靈魂卡攻擊時」須從自己牌組抽取1張卡牌。\n","info_43":null,"info_44":null,"info_45":null,"info_46":null,"info_47":null,"info_48":null,"info_49":null,"info_50":null,"delflg":"0","created":"2015-03-11 15:50:53","modified":"2015-03-11 15:50:53","rank":"94211","freewords":"BSC19-002 エビラ［2004］ スピリット 赤 ［Lv1-Lv2］『このスピリットのアタック時』<br />このスピリットをBP+3000する。 ［Lv2］『このスピリットのアタック時』<br />自分はデッキから1枚ドローする。   じ じ<br />じぶん まい  溶魚 ようぎょ  ","cost_icon":"<img src='../image/card_serch/icon_red.gif' />","faq":"沒有"},{"id":"94212","character_id":"62","prodid":"62065","subid":"2","info_1":"BSC19-003","info_2":"ミニラ［2004］","info_3":"スピリット","info_4":"赤","info_5":"2","info_6":"赤2","info_7":"1","info_8":"4000","info_9":"3","info_10":"6000","info_11":"4","info_12":"8000","info_13":"C","info_14":null,"info_15":null,"info_16":null,"info_17":"ゴジラの同族と思われるちびっこ怪獣。リング状の熱線しか吐けなかったが、<br />後に巨大化し、ゴジラのような熱線を吐けるようになる。<br />－ゴジラ FINALWARS（2004）－","info_18":null,"info_19":null,"info_20":null,"info_21":null,"info_22":null,"info_23":null,"info_24":null,"info_25":"地竜","info_26":"ちりゅう","info_27":"BSC19-003","info_28":"BSC19-003","info_29":null,"info_30":"-","info_31":null,"info_32":null,"info_33":null,"info_34":"-","info_35":null,"info_36":null,"info_37":null,"info_38":null,"info_39":null,"info_40":null,"info_41":"迷你拉[2004]","info_42":"\n","info_43":null,"info_44":null,"info_45":null,"info_46":null,"info_47":null,"info_48":null,"info_49":null,"info_50":null,"delflg":"0","created":"2015-03-11 15:50:53","modified":"2015-03-11 15:50:53","rank":"94212","freewords":"BSC19-003 ミニラ［2004］ スピリット 赤        地竜 ちりゅう  ","cost_icon":"<img src='../image/card_serch/icon_red.gif' /><img src='../image/card_serch/icon_red.gif' />","faq":"沒有"},{"id":"94213","character_id":"62","prodid":"62065","subid":"2","info_1":"BSC19-004","info_2":"アンギラス［2004］","info_3":"スピリット","info_4":"赤","info_5":"3","info_6":"赤2","info_7":"1","info_8":"3000","info_9":"2","info_10":"4000","info_11":"4","info_12":"5000","info_13":"R","info_14":"［Lv1-Lv2-Lv3］『このスピリットの召喚時』<br />相手のネクサス1つを破壊する。","info_15":"［Lv2-Lv3］<br />カード名に「ゴジラ」と入っている自分のスピリットがいる間、このスピリットをBP+5000する。","info_16":null,"info_17":"6万トンもある身体をボールのように丸め、<br />体当たり攻撃をする“アンギラスボール”で戦う。<br />－ゴジラ FINALWARS（2004）－","info_18":null,"info_19":null,"info_20":null,"info_21":null,"info_22":"しょうかんじ<br />あいて はかい","info_23":"めい はい じぶん あいだ","info_24":null,"info_25":"地竜","info_26":"ちりゅう","info_27":"BSC19-004","info_28":"BSC19-004","info_29":null,"info_30":"-","info_31":null,"info_32":null,"info_33":null,"info_34":"-","info_35":null,"info_36":null,"info_37":null,"info_38":null,"info_39":null,"info_40":null,"info_41":"安基拉斯(2004)","info_42":"LV1・LV2・LV3「這張靈魂卡召喚時」破壞對手1張核心卡。<br />LV2・LV3 場中有自己卡名中包含「ゴジラ」的靈魂卡期間，這張靈魂卡 +5000BP。\n","info_43":null,"info_44":null,"info_45":null,"info_46":null,"info_47":null,"info_48":null,"info_49":null,"info_50":null,"delflg":"0","created":"2015-03-11 15:50:53","modified":"2015-03-11 15:50:53","rank":"94213","freewords":"BSC19-004 アンギラス［2004］ スピリット 赤 ［Lv1-Lv2-Lv3］『このスピリットの召喚時』<br />相手のネクサス1つを破壊する。 ［Lv2-Lv3］<br />カード名に「ゴジラ」と入っている自分のスピリットがいる間、このスピリットをBP+5000する。   しょうかんじ<br />あいて はかい めい はい じぶん あいだ  地竜 ちりゅう  ","cost_icon":"<img src='../image/card_serch/icon_red.gif' /><img src='../image/card_serch/icon_red.gif' />","faq":"沒有"},{"id":"94214","character_id":"62","prodid":"62065","subid":"2","info_1":"BSC19-005","info_2":"リトルゴジラ","info_3":"スピリット","info_4":"赤","info_5":"3","info_6":"赤2","info_7":"1","info_8":"3000","info_9":"2","info_10":"4000","info_11":"5","info_12":"7000","info_13":"C","info_14":"［Lv1-Lv2-Lv3］『このスピリットの召喚時』<br />自分のデッキを上から3枚オープンできる。その中のカード名に「ゴジラ」と入っているスピリットカード1枚を手札に加える。残ったカードは好きな順番でデッキの下に戻す。","info_15":null,"info_16":null,"info_17":"バース島に生息しているベビーゴジラが成長した姿。<br />怪獣としての戦闘力はほとんどないが小さな熱線が吐ける。<br />－ゴジラvsスペースゴジラ（1994）－","info_18":null,"info_19":null,"info_20":null,"info_21":null,"info_22":"しょうかんじ<br />じぶん うえ まい なか　めい はい まい てふだ くわ のこ す じゅんばん した もど","info_23":null,"info_24":null,"info_25":"地竜","info_26":"ちりゅう","info_27":"BSC19-005","info_28":"BSC19-005","info_29":null,"info_30":"-","info_31":null,"info_32":null,"info_33":null,"info_34":"-","info_35":null,"info_36":null,"info_37":null,"info_38":null,"info_39":null,"info_40":null,"info_41":"小哥斯拉","info_42":"LV1・LV2・LV3「這張靈魂卡召喚時」可從自己牌組上公開3張卡牌，把當中1張卡名中包含「ゴジラ」的靈魂卡加進手牌。餘下的卡牌依喜好順序放至牌組最下。\n","info_43":null,"info_44":null,"info_45":null,"info_46":null,"info_47":null,"info_48":null,"info_49":null,"info_50":null,"delflg":"0","created":"2015-03-11 15:50:53","modified":"2015-03-11 15:50:53","rank":"94214","freewords":"BSC19-005 リトルゴジラ スピリット 赤 ［Lv1-Lv2-Lv3］『このスピリットの召喚時』<br />自分のデッキを上から3枚オープンできる。その中のカード名に「ゴジラ」と入っているスピリットカード1枚を手札に加える。残ったカードは好きな順番でデッキの下に戻す。    しょうかんじ<br />じぶん うえ まい なか　めい はい まい てふだ くわ のこ す じゅんばん した もど   地竜 ちりゅう  ","cost_icon":"<img src='../image/card_serch/icon_red.gif' /><img src='../image/card_serch/icon_red.gif' />","faq":"BSC19-005"},{"id":"94215","character_id":"62","prodid":"62065","subid":"2","info_1":"BSC19-006","info_2":"婆羅護吽","info_3":"スピリット","info_4":"赤","info_5":"3","info_6":"赤3","info_7":"1","info_8":"5000","info_9":"2","info_10":"7000","info_11":"3","info_12":"9000","info_13":"C","info_14":null,"info_15":null,"info_16":null,"info_17":"護国三聖獣の一体で地の神。<br />地底を掘削して移動をし、戦闘でも地中から奇襲をかける。<br />－ゴジラ モスラ キングギドラ　大怪獣総攻撃（2001）－","info_18":null,"info_19":null,"info_20":null,"info_21":"バラゴン","info_22":null,"info_23":null,"info_24":null,"info_25":"地竜","info_26":"ちりゅう","info_27":"BSC19-006","info_28":"BSC19-006","info_29":null,"info_30":"-","info_31":null,"info_32":null,"info_33":null,"info_34":"-","info_35":null,"info_36":null,"info_37":null,"info_38":null,"info_39":null,"info_40":null,"info_41":"婆羅護吽","info_42":"\n","info_43":null,"info_44":null,"info_45":null,"info_46":null,"info_47":null,"info_48":null,"info_49":null,"info_50":null,"delflg":"0","created":"2015-03-11 15:50:53","modified":"2015-03-11 15:50:53","rank":"94215","freewords":"BSC19-006 婆羅護吽 スピリット 赤    バラゴン    地竜 ちりゅう  ","cost_icon":"<img src='../image/card_serch/icon_red.gif' /><img src='../image/card_serch/icon_red.gif' /><img src='../image/card_serch/icon_red.gif' />","faq":"沒有"},{"id":"94216","character_id":"62","prodid":"62065","subid":"2","info_1":"BSC19-007","info_2":"ドラット","info_3":"スピリット","info_4":"赤","info_5":"4","info_6":"赤3","info_7":"1","info_8":"3000","info_9":"2","info_10":"4000","info_11":null,"info_12":"-","info_13":"C","info_14":"［Lv1-Lv2］『このスピリットの召喚時』<br />自分のデッキを上から5枚オープンできる。その中のカード名に「キングギドラ」と入っているスピリットカード1枚を手札に加える。残ったカードは好きな順番でデッキの下に戻す。","info_15":null,"info_16":null,"info_17":"未来人のペット用に遺伝子操作で生み出された。<br />核実験の放射能を浴びてキングギドラ化する。<br />-ゴジラvsキングギドラ（1991）-","info_18":null,"info_19":null,"info_20":null,"info_21":null,"info_22":"しょうかんじ<br />じぶん うえ まい なか めい はい まい てふだ くわ のこ す じゅんばん した もど","info_23":null,"info_24":null,"info_25":"翼竜","info_26":"よくりゅう","info_27":"BSC19-007","info_28":"BSC19-007","info_29":null,"info_30":"-","info_31":null,"info_32":null,"info_33":null,"info_34":"-","info_35":null,"info_36":null,"info_37":null,"info_38":null,"info_39":null,"info_40":null,"info_41":"多拉仔","info_42":"LV1・LV2「這張靈魂卡召喚時」可從自己牌組上公開5張卡牌，把當中1張卡名中包含「キングギドラ」的靈魂卡加進手牌。餘下的卡牌依喜好順序放至牌組最下。\n","info_43":null,"info_44":null,"info_45":null,"info_46":null,"info_47":null,"info_48":null,"info_49":null,"info_50":null,"delflg":"0","created":"2015-03-11 15:50:53","modified":"2015-03-11 15:50:53","rank":"94216","freewords":"BSC19-007 ドラット スピリット 赤 ［Lv1-Lv2］『このスピリットの召喚時』<br />自分のデッキを上から5枚オープンできる。その中のカード名に「キングギドラ」と入っているスピリットカード1枚を手札に加える。残ったカードは好きな順番でデッキの下に戻す。    しょうかんじ<br />じぶん うえ まい なか めい はい まい てふだ くわ のこ す じゅんばん した もど   翼竜 よくりゅう  ","cost_icon":"<img src='../image/card_serch/icon_red.gif' /><img src='../image/card_serch/icon_red.gif' /><img src='../image/card_serch/icon_red.gif' />","faq":"BSC19-007"},{"id":"94217","character_id":"62","prodid":"62065","subid":"2","info_1":"BSC19-008","info_2":"ラドン［2004］","info_3":"スピリット","info_4":"赤","info_5":"4","info_6":"赤3","info_7":"1","info_8":"3000","info_9":"2","info_10":"4000","info_11":"4","info_12":"5000","info_13":"U","info_14":"［Lv1-Lv2-Lv3］『このスピリットのアタック時』<br />BP3000以下の相手のスピリット1体を破壊する。","info_15":null,"info_16":null,"info_17":"アドノア島で眠っていた卵から誕生した翼竜プテラノドン。<br />鋭いクチバシと高速飛行で発生するソニックブームで敵を攻撃する。<br />－ゴジラ FINALWARS（2004）－","info_18":null,"info_19":null,"info_20":null,"info_21":null,"info_22":"じ<br />いか あいて たい はかい","info_23":null,"info_24":null,"info_25":"翼竜","info_26":"よくりゅう","info_27":"BSC19-008","info_28":"BSC19-008","info_29":null,"info_30":"-","info_31":null,"info_32":null,"info_33":null,"info_34":"-","info_35":null,"info_36":null,"info_37":null,"info_38":null,"info_39":null,"info_40":null,"info_41":"拉頓(2004)","info_42":"LV1・LV2・LV3「這張靈魂卡攻擊時」破壞對手1張BP3000或以下的靈魂卡。\n","info_43":null,"info_44":null,"info_45":null,"info_46":null,"info_47":null,"info_48":null,"info_49":null,"info_50":null,"delflg":"0","created":"2015-03-11 15:50:53","modified":"2015-03-11 15:50:53","rank":"94217","freewords":"BSC19-008 ラドン［2004］ スピリット 赤 ［Lv1-Lv2-Lv3］『このスピリットのアタック時』<br />BP3000以下の相手のスピリット1体を破壊する。    じ<br />いか あいて たい はかい   翼竜 よくりゅう  ","cost_icon":"<img src='../image/card_serch/icon_red.gif' /><img src='../image/card_serch/icon_red.gif' /><img src='../image/card_serch/icon_red.gif' />","faq":"沒有"},{"id":"94218","character_id":"62","prodid":"62065","subid":"2","info_1":"BSC19-009","info_2":"モンスターＸ","info_3":"スピリット","info_4":"赤","info_5":"5","info_6":"赤2","info_7":"1","info_8":"4000","info_9":"3","info_10":"7000","info_11":"4","info_12":"8000","info_13":"U","info_14":"［Lv1-Lv2-Lv3］【真・激突】『このスピリットのアタック時』<br />相手は可能ならスピリット/アルティメットでブロックする。","info_15":"［Lv2-Lv3］『このスピリットのアタック時』<br />自分はデッキから2枚ドローする。","info_16":null,"info_17":"3つの頭部から発射する引力光線“デストロイド・サンダー”は、<br />ゴジラを圧倒するパワーを持っている。<br />－ゴジラ FINALWARS（2004）－","info_18":null,"info_19":null,"info_20":null,"info_21":"gggggggggg","info_22":"しん げきとつ じ<br />あいて かのう","info_23":"じ<br />じぶん まい","info_24":null,"info_25":"星竜","info_26":"せいりゅう","info_27":"BSC19-009","info_28":"BSC19-009","info_29":null,"info_30":"-","info_31":null,"info_32":null,"info_33":null,"info_34":"-","info_35":null,"info_36":null,"info_37":null,"info_38":null,"info_39":null,"info_40":null,"info_41":"怪獸X","info_42":"LV1・LV2・LV3【真・激突】「這張靈魂卡攻擊時」對手靈魂卡/究極卡可以防禦時，必須防禦。<br />LV2・LV3「這張靈魂卡攻擊時」須從自己牌組抽取2張卡牌。\n","info_43":null,"info_44":null,"info_45":null,"info_46":null,"info_47":null,"info_48":null,"info_49":null,"info_50":null,"delflg":"0","created":"2015-03-11 15:50:54","modified":"2015-03-11 15:50:54","rank":"94218","freewords":"BSC19-009 モンスターＸ スピリット 赤 ［Lv1-Lv2-Lv3］【真・激突】『このスピリットのアタック時』<br />相手は可能ならスピリット/アルティメットでブロックする。 ［Lv2-Lv3］『このスピリットのアタック時』<br />自分はデッキから2枚ドローする。  gggggggggg しん げきとつ じ<br />あいて かのう じ<br />じぶん まい  星竜 せいりゅう  ","cost_icon":"<img src='../image/card_serch/icon_red.gif' /><img src='../image/card_serch/icon_red.gif' />","faq":"BSC19-009"},{"id":"94219","character_id":"62","prodid":"62065","subid":"2","info_1":"BSC19-010","info_2":"ガイガン［2004］","info_3":"スピリット","info_4":"赤","info_5":"5","info_6":"赤3","info_7":"1","info_8":"4000","info_9":"2","info_10":"6000","info_11":"5","info_12":"9000","info_13":"U","info_14":null,"info_15":"［Lv2-Lv3］『このスピリットのアタック時』<br />BP3000以下の相手のスピリット2体を破壊する。","info_16":null,"info_17":"機械と生物が融合したサイボーク怪獣。両腕のカマや胸部の回転カッター、<br />目から放つ赤いビームなどの多彩な武器で攻撃を仕掛ける。<br />－ゴジラ FINALWARS（2004）－<br />","info_18":null,"info_19":null,"info_20":null,"info_21":null,"info_22":null,"info_23":"じ<br />いか あいて たい はかい","info_24":null,"info_25":"星竜","info_26":"せいりゅう","info_27":"BSC19-010","info_28":"BSC19-010","info_29":null,"info_30":"-","info_31":null,"info_32":null,"info_33":null,"info_34":"-","info_35":null,"info_36":null,"info_37":null,"info_38":null,"info_39":null,"info_40":null,"info_41":"蓋剛[2004]","info_42":"LV2・LV3「這張靈魂卡攻擊時」破壞對手2張BP3000或以下的靈魂卡。\n","info_43":null,"info_44":null,"info_45":null,"info_46":null,"info_47":null,"info_48":null,"info_49":null,"info_50":null,"delflg":"0","created":"2015-03-11 15:50:54","modified":"2015-03-11 15:50:54","rank":"94219","freewords":"BSC19-010 ガイガン［2004］ スピリット 赤  ［Lv2-Lv3］『このスピリットのアタック時』<br />BP3000以下の相手のスピリット2体を破壊する。    じ<br />いか あいて たい はかい  星竜 せいりゅう  ","cost_icon":"<img src='../image/card_serch/icon_red.gif' /><img src='../image/card_serch/icon_red.gif' /><img src='../image/card_serch/icon_red.gif' />","faq":"沒有"},{"id":"94220","character_id":"62","prodid":"62065","subid":"2","info_1":"BSC19-011","info_2":"ゴジラジュニア","info_3":"スピリット","info_4":"赤","info_5":"5","info_6":"赤3","info_7":"1","info_8":"4000","info_9":"2","info_10":"6000","info_11":"4","info_12":"8000","info_13":"C","info_14":"[Lv1-Lv2-Lv3]『このスピリットのアタック時』<br />相手のネクサス1つを破壊する。","info_15":null,"info_16":"[Lv3]『このスピリットのアタック時』<br />回復状態の相手のスピリット1体を指定し、そのスピリットにアタックできる。","info_17":"リトルゴジラがバース島の核分裂の反応で成長をした姿。<br />熱線の威力もパワーアップをしている。<br />後にメルトダウンをしたゴジラの放射能を吸収し、新たなゴジラへと姿を変える。<br />－ゴジラvsデストロイア（1995）－","info_18":null,"info_19":null,"info_20":null,"info_21":null,"info_22":"じ<br />あいて はかい","info_23":null,"info_24":"じ<br />かいふくじょうたい あいて たい してい","info_25":"地竜","info_26":"ちりゅう","info_27":"BSC19-011","info_28":"BSC19-011","info_29":null,"info_30":"-","info_31":null,"info_32":null,"info_33":null,"info_34":"-","info_35":null,"info_36":null,"info_37":null,"info_38":null,"info_39":null,"info_40":null,"info_41":"哥斯拉Jr.","info_42":"LV1・LV2・LV3「這張靈魂卡攻擊時」破壞對手1張核心卡。<br />LV3「這張靈魂卡攻擊時」指定對手1張回復狀態的靈魂卡，並對該靈魂卡進行攻擊。\n","info_43":null,"info_44":null,"info_45":null,"info_46":null,"info_47":null,"info_48":null,"info_49":null,"info_50":null,"delflg":"0","created":"2015-03-11 15:50:54","modified":"2015-03-11 15:50:54","rank":"94220","freewords":"BSC19-011 ゴジラジュニア スピリット 赤 [Lv1-Lv2-Lv3]『このスピリットのアタック時』<br />相手のネクサス1つを破壊する。  [Lv3]『このスピリットのアタック時』<br />回復状態の相手のスピリット1体を指定し、そのスピリットにアタックできる。  じ<br />あいて はかい  じ<br />かいふくじょうたい あいて たい してい 地竜 ちりゅう  ","cost_icon":"<img src='../image/card_serch/icon_red.gif' /><img src='../image/card_serch/icon_red.gif' /><img src='../image/card_serch/icon_red.gif' />","faq":"沒有"},{"id":"94221","character_id":"62","prodid":"62065","subid":"2","info_1":"BSC19-012","info_2":"デストロイア（集合体）","info_3":"スピリット","info_4":"赤","info_5":"6","info_6":"赤3","info_7":"1","info_8":"3000","info_9":"3","info_10":"5000","info_11":null,"info_12":"-","info_13":"U","info_14":"カード名に「デストロイア」と入っている自分のスピリットが3体以上いる間、手札にあるこのスピリットカードを召喚するとき、コスト3として扱う。<br />［Lv1-Lv2］『このスピリットの召喚時』<br />BP5000以下の相手のスピリット1体を破壊する。この効果でスピリットを破壊したとき、自分はデッキから1枚ドローする。","info_15":null,"info_16":null,"info_17":"複数の幼体が集合合体した姿。攻撃用の長い触手とハサミが特徴。<br />口から伸ばした口吻からミクロオキシゲンを注入できる。<br />－ゴジラvsデストロイア（1995）－","info_18":null,"info_19":null,"info_20":null,"info_21":"しゅうごうたい","info_22":"てふだ めい はい じぶん たいいじょうしはら しょうかん<br />しょうかんじ<br />いか あいて たい はかい こうか はかい じぶん まい","info_23":null,"info_24":null,"info_25":"爬獣","info_26":"はじゅう","info_27":"BSC19-012","info_28":"BSC19-012","info_29":null,"info_30":"-","info_31":null,"info_32":null,"info_33":null,"info_34":"-","info_35":null,"info_36":null,"info_37":null,"info_38":null,"info_39":null,"info_40":null,"info_41":"戴斯特洛伊亞(集合體)","info_42":"自己有3張或以上卡名中包含「デストロイア」的靈魂卡期間，從手牌中召喚這張靈魂卡時，當作需求 3。<br />LV1・LV2「這張靈魂卡召喚時」破壞對手1張BP5000或以下的靈魂卡。這效果破壞靈魂卡時，須從自己牌組抽取1張卡牌。\n","info_43":null,"info_44":null,"info_45":null,"info_46":null,"info_47":null,"info_48":null,"info_49":null,"info_50":null,"delflg":"0","created":"2015-03-11 15:50:54","modified":"2015-03-11 15:50:54","rank":"94221","freewords":"BSC19-012 デストロイア（集合体） スピリット 赤 カード名に「デストロイア」と入っている自分のスピリットが3体以上いる間、手札にあるこのスピリットカードを召喚するとき、コスト3として扱う。<br />［Lv1-Lv2］『このスピリットの召喚時』<br />BP5000以下の相手のスピリット1体を破壊する。この効果でスピリットを破壊したとき、自分はデッキから1枚ドローする。   しゅうごうたい てふだ めい はい じぶん たいいじょうしはら しょうかん<br />しょうかんじ<br />いか あいて たい はかい こうか はかい じぶん まい   爬獣 はじゅう  ","cost_icon":"<img src='../image/card_serch/icon_red.gif' /><img src='../image/card_serch/icon_red.gif' /><img src='../image/card_serch/icon_red.gif' />","faq":"沒有"},{"id":"94222","character_id":"62","prodid":"62065","subid":"2","info_1":"BSC19-013","info_2":"ファイヤーラドン","info_3":"スピリット","info_4":"赤","info_5":"7","info_6":"赤4","info_7":"1","info_8":"5000","info_9":"3","info_10":"8000","info_11":"4","info_12":"12000","info_13":"R","info_14":"［Lv1-Lv2-Lv3］『このスピリットのアタック時』<br />BP5000以下の相手のスピリット1体を破壊する。<br />［Lv1-Lv2-Lv3］『このスピリットの破壊時』<br />自分のトラッシュにある、カード名に「ゴジラ」と入っている赤のスピリットカード1枚を、コストを支払わずに召喚できる。","info_15":null,"info_16":null,"info_17":"ラドンの全身が赤くなり復活をした姿。<br />口から熱線を吐けるようになった。<br />－ゴジラvsメカゴジラ（1993）－","info_18":null,"info_19":null,"info_20":null,"info_21":null,"info_22":"じ<br />いか あいて たい はかい<br />はかいじ<br />じぶん めい はい あか まい しはら しょうかん","info_23":null,"info_24":null,"info_25":"翼竜","info_26":"よくりゅう","info_27":"BSC19-013","info_28":"BSC19-013","info_29":null,"info_30":"-","info_31":null,"info_32":null,"info_33":null,"info_34":"-","info_35":null,"info_36":null,"info_37":null,"info_38":null,"info_39":null,"info_40":null,"info_41":"火焰拉頓","info_42":"LV1・LV2・LV3「這張靈魂卡攻擊時」破壞對手1張BP5000或以下的靈魂卡。<br />LV1・LV2・LV3「這張靈魂卡被破壞時」自己廢棄區中1張卡名中包含「ゴジラ」的紅色靈魂卡，無需支付需求召喚到場中。\n","info_43":null,"info_44":null,"info_45":null,"info_46":null,"info_47":null,"info_48":null,"info_49":null,"info_50":null,"delflg":"0","created":"2015-03-11 15:50:54","modified":"2015-03-11 15:50:54","rank":"94222","freewords":"BSC19-013 ファイヤーラドン スピリット 赤 ［Lv1-Lv2-Lv3］『このスピリットのアタック時』<br />BP5000以下の相手のスピリット1体を破壊する。<br />［Lv1-Lv2-Lv3］『このスピリットの破壊時』<br />自分のトラッシュにある、カード名に「ゴジラ」と入っている赤のスピリットカード1枚を、コストを支払わずに召喚できる。    じ<br />いか あいて たい はかい<br />はかいじ<br />じぶん めい はい あか まい しはら しょうかん   翼竜 よくりゅう  ","cost_icon":"<img src='../image/card_serch/icon_red.gif' /><img src='../image/card_serch/icon_red.gif' /><img src='../image/card_serch/icon_red.gif' /><img src='../image/card_serch/icon_red.gif' />","faq":"BSC19-013"},{"id":"94223","character_id":"62","prodid":"62065","subid":"2","info_1":"BSC19-014","info_2":"千年竜王・魏怒羅","info_3":"スピリット","info_4":"赤","info_5":"8","info_6":"赤4","info_7":"1","info_8":"6000","info_9":"2","info_10":"8000","info_11":"3","info_12":"10000","info_13":"R","info_14":"このスピリット/スピリットカードはカード名に「キングギドラ」が入っているものとして扱う。<br />［Lv1-Lv2-Lv3］『このスピリットのアタック時』<br />BP3000以下の相手のスピリット1体を破壊する。","info_15":"［Lv2-Lv3］『このスピリットのアタック時』<br />BP5000以下の相手のスピリット1体を破壊する。","info_16":"［Lv3］『このスピリットのアタック時』<br />BP7000以下の相手のスピリット1体を破壊する。","info_17":"護国三聖獣の一体で天の神。<br />完全体になることで引力光線などを使うことができるようになる。<br />－ゴジラ モスラ キングギドラ　大怪獣総攻撃（2001）－","info_18":null,"info_19":null,"info_20":null,"info_21":"せんねんりゅうおう ギドラ","info_22":"めい はい あつか<br />じ<br />いか あいて たい はかい","info_23":"じ<br />いか あいて たい はかい","info_24":"じ<br />いか あいて たい はかい","info_25":"古竜","info_26":"こりゅう","info_27":"BSC19-014","info_28":"BSC19-014","info_29":null,"info_30":"-","info_31":null,"info_32":null,"info_33":null,"info_34":"-","info_35":null,"info_36":null,"info_37":null,"info_38":null,"info_39":null,"info_40":null,"info_41":"千年龍王．魏怒羅","info_42":"這張靈魂/靈魂卡，當作卡名中包含「キングギドラ」來使用。<br />LV1・LV2・LV3「這張靈魂卡攻擊時」破壞對手1張BP3000或以下的靈魂卡。<br />LV2・LV3「這張靈魂卡攻擊時」破壞對手1張BP 5000或以下的靈魂卡。<br />LV3「這張靈魂卡攻擊時」破壞對手1張BP 7000或以下的靈魂卡。\n","info_43":null,"info_44":null,"info_45":null,"info_46":null,"info_47":null,"info_48":null,"info_49":null,"info_50":null,"delflg":"0","created":"2015-03-11 15:50:54","modified":"2015-03-11 15:50:54","rank":"94223","freewords":"BSC19-014 千年竜王・魏怒羅 スピリット 赤 このスピリット/スピリットカードはカード名に「キングギドラ」が入っているものとして扱う。<br />［Lv1-Lv2-Lv3］『このスピリットのアタック時』<br />BP3000以下の相手のスピリット1体を破壊する。 ［Lv2-Lv3］『このスピリットのアタック時』<br />BP5000以下の相手のスピリット1体を破壊する。 ［Lv3］『このスピリットのアタック時』<br />BP7000以下の相手のスピリット1体を破壊する。 せんねんりゅうおう ギドラ めい はい あつか<br />じ<br />いか あいて たい はかい じ<br />いか あいて たい はかい じ<br />いか あいて たい はかい 古竜 こりゅう  ","cost_icon":"<img src='../image/card_serch/icon_red.gif' /><img src='../image/card_serch/icon_red.gif' /><img src='../image/card_serch/icon_red.gif' /><img src='../image/card_serch/icon_red.gif' />","faq":"BSC19-014"},{"id":"94224","character_id":"62","prodid":"62065","subid":"2","info_1":"BSC19-015","info_2":"カイザーギドラ","info_3":"スピリット","info_4":"赤","info_5":"10","info_6":"赤6","info_7":"1","info_8":"10000","info_9":"3","info_10":"15000","info_11":"5","info_12":"20000","info_13":"M","info_14":"手札にあるこのスピリットカードは、自分の[モンスターＸ]が相手によって破壊されたとき、コストを支払わずに召喚できる。<br />［Lv1-Lv2-Lv3］『このスピリットの召喚時』<br />BP合計15000まで相手のスピリット/アルティメットを好きなだけ破壊する。","info_15":null,"info_16":null,"info_17":"モンスターXが変身した最強の形態。<br />3つの口から放つ反重力光線“デストロイド・カイザー”を武器に闘う。<br />相手に噛みつきエネルギーを吸収する。－ゴジラ FINAL WARS（2004）－","info_18":null,"info_19":null,"info_20":null,"info_21":null,"info_22":"てふだ じぶん エックス あいて はかい しはら しょうかん<br />しょうかんじ<br />ごうけい あいて す はかい","info_23":null,"info_24":null,"info_25":"星竜・皇獣","info_26":"せいりゅう　こうじゅう","info_27":"BSC19-015","info_28":"BSC19-015","info_29":null,"info_30":"-","info_31":null,"info_32":null,"info_33":null,"info_34":"-","info_35":null,"info_36":null,"info_37":null,"info_38":null,"info_39":null,"info_40":null,"info_41":"凱薩基多拉","info_42":"手牌中的這張靈魂卡在自己的[モンスターX]被對手破壞時，無需支付需求召喚到場中。<br />LV1・LV2・LV3「這張靈魂卡召喚時」隨喜好不限數量地破壞對手BP合計15000為止的靈魂卡/究極卡。\n","info_43":null,"info_44":null,"info_45":null,"info_46":null,"info_47":null,"info_48":null,"info_49":null,"info_50":null,"delflg":"0","created":"2015-03-11 15:50:54","modified":"2015-03-11 15:50:54","rank":"94224","freewords":"BSC19-015 カイザーギドラ スピリット 赤 手札にあるこのスピリットカードは、自分の[モンスターＸ]が相手によって破壊されたとき、コストを支払わずに召喚できる。<br />［Lv1-Lv2-Lv3］『このスピリットの召喚時』<br />BP合計15000まで相手のスピリット/アルティメットを好きなだけ破壊する。    てふだ じぶん エックス あいて はかい しはら しょうかん<br />しょうかんじ<br />ごうけい あいて す はかい   星竜・皇獣 せいりゅう　こうじゅう  ","cost_icon":"<img src='../image/card_serch/icon_red.gif' /><img src='../image/card_serch/icon_red.gif' /><img src='../image/card_serch/icon_red.gif' /><img src='../image/card_serch/icon_red.gif' /><img src='../image/card_serch/icon_red.gif' /><img src='../image/card_serch/icon_red.gif' />","faq":"BSC19-015"},{"id":"94225","character_id":"62","prodid":"62065","subid":"2","info_1":"BSC19-016","info_2":"オルガ","info_3":"スピリット","info_4":"赤・白","info_5":"6","info_6":"赤2白2","info_7":"1","info_8":"3000","info_9":"3","info_10":"5000","info_11":"4","info_12":"7000","info_13":"M","info_14":"［バースト：自分のライフ減少後］<br />このスピリットカードを召喚する。その後、自分のライフが5以下のとき、ボイドからコア1個を自分のライフに置く。","info_15":"［Lv2-Lv3］『このスピリットのバトル時』<br />BP3000以下の相手のスピリット1体を破壊する。","info_16":"［Lv3］『このスピリットの破壊時』<br />このスピリットは手札に戻る。","info_17":"ゴジラの持つオルガナイザーＧ1を取り込んだが、<br />制御しきれなかったミレニアンが怪獣化した姿。<br />再生力が非常に高い。　－ゴジラ2000 ミレニアム（1999）－","info_18":null,"info_19":null,"info_20":null,"info_21":null,"info_22":"じぶん げんしょうご<br />しょうかん ご じぶん いか こ じぶん お","info_23":"じ<br />いか あいて たい はかい","info_24":"はかいじ<br />てふだ もど","info_25":"星竜","info_26":"せいりゅう","info_27":"BSC19-016","info_28":"BSC19-016","info_29":null,"info_30":"-","info_31":null,"info_32":null,"info_33":null,"info_34":"-","info_35":null,"info_36":null,"info_37":null,"info_38":null,"info_39":null,"info_40":null,"info_41":"歐魯卡","info_42":"【Burst：自己生命值減少後】<br />召喚這張靈魂卡。然後，自己生命值5個或以下，從空間取1個能量至自己生命值。<br />LV2・LV3「這張靈魂卡戰鬥時」破壞對手1張BP3000或以下的靈魂卡<br />LV3「這張靈魂卡破壞時」這張靈魂卡回到手牌。\n","info_43":null,"info_44":null,"info_45":null,"info_46":null,"info_47":null,"info_48":null,"info_49":null,"info_50":null,"delflg":"0","created":"2015-03-11 15:50:54","modified":"2015-03-11 15:50:54","rank":"94225","freewords":"BSC19-016 オルガ スピリット 赤・白 ［バースト：自分のライフ減少後］<br />このスピリットカードを召喚する。その後、自分のライフが5以下のとき、ボイドからコア1個を自分のライフに置く。 ［Lv2-Lv3］『このスピリットのバトル時』<br />BP3000以下の相手のスピリット1体を破壊する。 ［Lv3］『このスピリットの破壊時』<br />このスピリットは手札に戻る。  じぶん げんしょうご<br />しょうかん ご じぶん いか こ じぶん お じ<br />いか あいて たい はかい はかいじ<br />てふだ もど 星竜 せいりゅう  ","cost_icon":"<img src='../image/card_serch/icon_red.gif' /><img src='../image/card_serch/icon_red.gif' /><img src='../image/card_serch/icon_white.gif' /><img src='../image/card_serch/icon_white.gif' />","faq":"BSC19-016"},{"id":"94226","character_id":"62","prodid":"62065","subid":"2","info_1":"BSC19-017","info_2":"妖精モスラ","info_3":"スピリット","info_4":"緑","info_5":"1","info_6":"-","info_7":"1","info_8":"1000","info_9":"2","info_10":"2000","info_11":null,"info_12":"-","info_13":"C","info_14":"［フラッシュ］【神速】<br />手札にあるこのスピリットカードは、召喚コストの支払いと上に置くコアをリザーブから使用することで召喚できる。","info_15":null,"info_16":null,"info_17":"モスラがスペースゴジラの脅威を伝えるため、<br />地球に派遣した分身の姿。<br />－ゴジラvsスペースゴジラ（1994）－","info_18":null,"info_19":null,"info_20":null,"info_21":"フェアリー","info_22":"しんそく<br />てふだ しょうかん しはら うえ お しよう しょうかん","info_23":null,"info_24":null,"info_25":"怪虫・漂精","info_26":"かいちゅう　ひょうせい","info_27":"BSC19-017","info_28":"BSC19-017","info_29":null,"info_30":"-","info_31":null,"info_32":null,"info_33":null,"info_34":"-","info_35":null,"info_36":null,"info_37":null,"info_38":null,"info_39":null,"info_40":null,"info_41":"妖精莫斯拉","info_42":"靈動【神速】可以召喚手牌中的這張靈魂卡，召喚和維持LV的能量須從預備區支付。\n","info_43":null,"info_44":null,"info_45":null,"info_46":null,"info_47":null,"info_48":null,"info_49":null,"info_50":null,"delflg":"0","created":"2015-03-11 15:50:54","modified":"2015-03-11 15:50:54","rank":"94226","freewords":"BSC19-017 妖精モスラ スピリット 緑 ［フラッシュ］【神速】<br />手札にあるこのスピリットカードは、召喚コストの支払いと上に置くコアをリザーブから使用することで召喚できる。   フェアリー しんそく<br />てふだ しょうかん しはら うえ お しよう しょうかん   怪虫・漂精 かいちゅう　ひょうせい  ","cost_icon":"","faq":"BSC19-017"},{"id":"94227","character_id":"62","prodid":"62065","subid":"2","info_1":"BSC19-018","info_2":"カマキラス［2004］","info_3":"スピリット","info_4":"緑","info_5":"2","info_6":"緑2","info_7":"1","info_8":"5000","info_9":"3","info_10":"7000","info_11":null,"info_12":"-","info_13":"C","info_14":null,"info_15":null,"info_16":null,"info_17":"オオカマキリが巨大化した怪獣。<br />両腕のカマによる攻撃を行い、保護色で周囲に溶け込む能力を持つ。<br />対ゴジラ戦では瞬殺された。<br />－ゴジラ FINALWARS（2004）－","info_18":null,"info_19":null,"info_20":null,"info_21":null,"info_22":null,"info_23":null,"info_24":null,"info_25":"怪虫","info_26":"かいちゅう","info_27":"BSC19-018","info_28":"BSC19-018","info_29":null,"info_30":"-","info_31":null,"info_32":null,"info_33":null,"info_34":"-","info_35":null,"info_36":null,"info_37":null,"info_38":null,"info_39":null,"info_40":null,"info_41":"卡馬奇拉斯","info_42":"\n","info_43":null,"info_44":null,"info_45":null,"info_46":null,"info_47":null,"info_48":null,"info_49":null,"info_50":null,"delflg":"0","created":"2015-03-11 15:50:54","modified":"2015-03-11 15:50:54","rank":"94227","freewords":"BSC19-018 カマキラス［2004］ スピリット 緑        怪虫 かいちゅう  ","cost_icon":"<img src='../image/card_serch/icon_green.gif' /><img src='../image/card_serch/icon_green.gif' />","faq":"沒有"},{"id":"94228","character_id":"62","prodid":"62065","subid":"2","info_1":"BSC19-019","info_2":"モスラ（幼虫）［1992］","info_3":"スピリット","info_4":"緑","info_5":"3","info_6":"緑1","info_7":"1","info_8":"2000","info_9":"3","info_10":"3000","info_11":null,"info_12":"-","info_13":"C","info_14":"［Lv1-Lv2］『このスピリットの召喚時』<br />ボイドからコア1個をこのスピリットに置く。","info_15":null,"info_16":null,"info_17":"地球の先住民であるコスモスの守護神。<br />インファント島で卵が発見された。<br />－ゴジラvsモスラ（1992）－","info_18":null,"info_19":null,"info_20":null,"info_21":"ようちゅう","info_22":"しょうかんじ<br />こ お","info_23":null,"info_24":null,"info_25":"怪虫","info_26":"かいちゅう","info_27":"BSC19-019","info_28":"BSC19-019","info_29":null,"info_30":"-","info_31":null,"info_32":null,"info_33":null,"info_34":"-","info_35":null,"info_36":null,"info_37":null,"info_38":null,"info_39":null,"info_40":null,"info_41":"莫斯拉(幼蟲)[1992]","info_42":"LV1・LV2「這張靈魂卡召喚時」從空間取1個能量至這張靈魂卡上。\n","info_43":null,"info_44":null,"info_45":null,"info_46":null,"info_47":null,"info_48":null,"info_49":null,"info_50":null,"delflg":"0","created":"2015-03-11 15:50:54","modified":"2015-03-11 15:50:54","rank":"94228","freewords":"BSC19-019 モスラ（幼虫）［1992］ スピリット 緑 ［Lv1-Lv2］『このスピリットの召喚時』<br />ボイドからコア1個をこのスピリットに置く。   ようちゅう しょうかんじ<br />こ お   怪虫 かいちゅう  ","cost_icon":"<img src='../image/card_serch/icon_green.gif' />","faq":"沒有"},{"id":"94229","character_id":"62","prodid":"62065","subid":"2","info_1":"BSC19-020","info_2":"キングシーサー［2004］","info_3":"スピリット","info_4":"緑","info_5":"4","info_6":"緑2","info_7":"1","info_8":"5000","info_9":"3","info_10":"10000","info_11":"4","info_12":"12000","info_13":"C","info_14":null,"info_15":null,"info_16":null,"info_17":"沖縄に出現した怪獣。身軽な動きが特徴。<br />“タックルブレイク”や“フライング・シーサーアタック”などの格闘技を使う。<br />怒ると耳を立てて威嚇をする。　－ゴジラ FINALWARS（2004）－","info_18":null,"info_19":null,"info_20":null,"info_21":null,"info_22":null,"info_23":null,"info_24":null,"info_25":"剣獣","info_26":"けんじゅう","info_27":"BSC19-020","info_28":"BSC19-020","info_29":null,"info_30":"-","info_31":null,"info_32":null,"info_33":null,"info_34":"-","info_35":null,"info_36":null,"info_37":null,"info_38":null,"info_39":null,"info_40":null,"info_41":"西薩王[2004]","info_42":"\n","info_43":null,"info_44":null,"info_45":null,"info_46":null,"info_47":null,"info_48":null,"info_49":null,"info_50":null,"delflg":"0","created":"2015-03-11 15:50:54","modified":"2015-03-11 15:50:54","rank":"94229","freewords":"BSC19-020 キングシーサー［2004］ スピリット 緑        剣獣 けんじゅう  ","cost_icon":"<img src='../image/card_serch/icon_green.gif' /><img src='../image/card_serch/icon_green.gif' />","faq":"沒有"},{"id":"94230","character_id":"62","prodid":"62065","subid":"2","info_1":"BSC19-021","info_2":"メガギラス","info_3":"スピリット","info_4":"緑","info_5":"4","info_6":"緑2","info_7":"1","info_8":"2000","info_9":"3","info_10":"4000","info_11":null,"info_12":"-","info_13":"M","info_14":"［フラッシュ］【神速】<br />手札にあるこのスピリットカードは、召喚コストの支払いと上に置くコアをリザーブから使用することで召喚できる。<br />［Lv1-Lv2］『このスピリットの召喚時』<br />相手のスピリット1体を疲労させる。","info_15":null,"info_16":null,"info_17":"メガニューラが群れの中から1匹を選び巨大化をさせた究極体。<br />巨大な鋏と大きな羽を羽ばたかせて発生させる高周波が特徴。<br />－ゴジラ×メガギラス（2000）－","info_18":null,"info_19":null,"info_20":null,"info_21":null,"info_22":"しんそく<br />てふだ しょうかん しはら うえ お しよう しょうかん<br />しょうかんじ<br />あいて たい ひろう","info_23":null,"info_24":null,"info_25":"怪虫","info_26":"かいちゅう","info_27":"BSC19-021","info_28":"BSC19-021","info_29":null,"info_30":"-","info_31":null,"info_32":null,"info_33":null,"info_34":"-","info_35":null,"info_36":null,"info_37":null,"info_38":null,"info_39":null,"info_40":null,"info_41":"米加基拉斯","info_42":"靈動【神速】可以召喚手牌中的這張靈魂卡，召喚和維持LV的能量須從預備區支付。<br />LV1・LV2「這張靈魂卡召喚時」對手1張靈魂卡變成疲勞狀態。\n","info_43":null,"info_44":null,"info_45":null,"info_46":null,"info_47":null,"info_48":null,"info_49":null,"info_50":null,"delflg":"0","created":"2015-03-11 15:50:54","modified":"2015-03-11 15:50:54","rank":"94230","freewords":"BSC19-021 メガギラス スピリット 緑 ［フラッシュ］【神速】<br />手札にあるこのスピリットカードは、召喚コストの支払いと上に置くコアをリザーブから使用することで召喚できる。<br />［Lv1-Lv2］『このスピリットの召喚時』<br />相手のスピリット1体を疲労させる。    しんそく<br />てふだ しょうかん しはら うえ お しよう しょうかん<br />しょうかんじ<br />あいて たい ひろう   怪虫 かいちゅう  ","cost_icon":"<img src='../image/card_serch/icon_green.gif' /><img src='../image/card_serch/icon_green.gif' />","faq":"BSC19-021"},{"id":"94231","character_id":"62","prodid":"62065","subid":"2","info_1":"BSC19-022","info_2":"ビオランテ（花獣形態）","info_3":"スピリット","info_4":"緑","info_5":"4","info_6":"緑3","info_7":"1","info_8":"3000","info_9":"3","info_10":"5000","info_11":null,"info_12":"-","info_13":"R","info_14":"［Lv1-Lv2］『相手のアタックステップ』<br />自分のライフが減ったとき、ボイドからコア1個をこのスピリットに置く。","info_15":"［Lv2］『このスピリットの破壊時』<br />自分の手札にあるカード名に「ビオランテ」と入っているスピリットカード1枚を、コストを支払わずに召喚できる。","info_16":null,"info_17":"白神源壱郎博士が娘の細胞とバラの細胞、<br />そしてゴジラ細胞を融合させて生み出した生命体。<br />-ゴジラvsビオランテ（1989）-","info_18":null,"info_19":null,"info_20":null,"info_21":"かじゅうけいたい","info_22":"あいて<br />じぶん へ こ お","info_23":"はかいじ<br />じぶん てふだ めい はい まい しはら しょうかん","info_24":null,"info_25":"樹魔","info_26":"じゅま","info_27":"BSC19-022","info_28":"BSC19-022","info_29":null,"info_30":"-","info_31":null,"info_32":null,"info_33":null,"info_34":"-","info_35":null,"info_36":null,"info_37":null,"info_38":null,"info_39":null,"info_40":null,"info_41":"碧奧蘭蒂(花獸形態)","info_42":"LV1・LV2「對手的攻擊階段」自己生命值被削減時，從空間取1個能量至這張靈魂卡上。<br />LV2「這張靈魂卡被破壞時」自己手牌中1張卡名中包含「ビオランテ」的靈魂卡，可無需支付需求召喚到場中。\n","info_43":null,"info_44":null,"info_45":null,"info_46":null,"info_47":null,"info_48":null,"info_49":null,"info_50":null,"delflg":"0","created":"2015-03-11 15:50:54","modified":"2015-03-11 15:50:54","rank":"94231","freewords":"BSC19-022 ビオランテ（花獣形態） スピリット 緑 ［Lv1-Lv2］『相手のアタックステップ』<br />自分のライフが減ったとき、ボイドからコア1個をこのスピリットに置く。 ［Lv2］『このスピリットの破壊時』<br />自分の手札にあるカード名に「ビオランテ」と入っているスピリットカード1枚を、コストを支払わずに召喚できる。  かじゅうけいたい あいて<br />じぶん へ こ お はかいじ<br />じぶん てふだ めい はい まい しはら しょうかん  樹魔 じゅま  ","cost_icon":"<img src='../image/card_serch/icon_green.gif' /><img src='../image/card_serch/icon_green.gif' /><img src='../image/card_serch/icon_green.gif' />","faq":"BSC19-022"},{"id":"94232","character_id":"62","prodid":"62065","subid":"2","info_1":"BSC19-023","info_2":"最珠羅","info_3":"スピリット","info_4":"緑","info_5":"5","info_6":"緑2","info_7":"1","info_8":"4000","info_9":"3","info_10":"6000","info_11":null,"info_12":"-","info_13":"U","info_14":"このスピリット/スピリットカードはカード名に「モスラ」が入っているものとして扱う。<br />［Lv1-Lv2］『このスピリットのアタック時』<br />相手のスピリット1体を疲労させる。","info_15":"［Lv2］『このスピリットのアタック時』<br />相手はバーストを発動できない。","info_16":null,"info_17":"護国三聖獣の1体で海の神。<br />幼虫時代は湖底に潜っていたが、<br />成虫になるとゴジラ熱線を回避するほどの飛行能力を得る。<br />－ゴジラ モスラ キングギドラ　大怪獣総攻撃（2001）－","info_18":null,"info_19":null,"info_20":null,"info_21":"モスラ","info_22":"めい はい あつか<br />じ<br />あいて たい ひろう","info_23":"じ<br />あいて はつどう","info_24":null,"info_25":"怪虫","info_26":"かいちゅう","info_27":"BSC19-023","info_28":"BSC19-023","info_29":null,"info_30":"-","info_31":null,"info_32":null,"info_33":null,"info_34":"-","info_35":null,"info_36":null,"info_37":null,"info_38":null,"info_39":null,"info_40":null,"info_41":"最珠羅","info_42":"這張靈魂卡，當作卡名中包含「モスラ」來使用。<br />LV1・LV2「這張靈魂卡攻擊時」對手1張靈魂卡變成疲勞狀態。<br />LV2「這張靈魂卡攻擊時」對手不能發動Burst。\n","info_43":null,"info_44":null,"info_45":null,"info_46":null,"info_47":null,"info_48":null,"info_49":null,"info_50":null,"delflg":"0","created":"2015-03-11 15:50:54","modified":"2015-03-11 15:50:54","rank":"94232","freewords":"BSC19-023 最珠羅 スピリット 緑 このスピリット/スピリットカードはカード名に「モスラ」が入っているものとして扱う。<br />［Lv1-Lv2］『このスピリットのアタック時』<br />相手のスピリット1体を疲労させる。 ［Lv2］『このスピリットのアタック時』<br />相手はバーストを発動できない。  モスラ めい はい あつか<br />じ<br />あいて たい ひろう じ<br />あいて はつどう  怪虫 かいちゅう  ","cost_icon":"<img src='../image/card_serch/icon_green.gif' /><img src='../image/card_serch/icon_green.gif' />","faq":"BSC19-023"},{"id":"94233","character_id":"62","prodid":"62065","subid":"2","info_1":"BSC19-024","info_2":"ビオランテ（植獣形態）","info_3":"スピリット","info_4":"緑","info_5":"7","info_6":"緑3","info_7":"1","info_8":"12000","info_9":"4","info_10":"17000","info_11":"8","info_12":"22000","info_13":"M","info_14":"［Lv1-Lv2-Lv3］『このスピリットの召喚時』<br />ボイドからコア2個をこのスピリットに置く。","info_15":"［Lv2-Lv3］『このスピリットのアタック時』<br />相手のスピリット/アルティメット1体を疲労させる。そのスピリット/アルティメットは次の『相手のリフレッシュステップ』で回復できない。","info_16":null,"info_17":"芦ノ湖で胞子となって消えたビオランテが進化した形態。<br />口や触手の先端から、強酸性の樹液を吐く。<br />-ゴジラvsビオランテ（1989）-","info_18":null,"info_19":null,"info_20":null,"info_21":"しょくじゅうけいたい","info_22":"しょうかんじ<br />こ お","info_23":"じ<br />あいて たい ひろう つぎ あいて かいふく","info_24":null,"info_25":"樹魔・古竜","info_26":"じゅま　こりゅう","info_27":"BSC19-024","info_28":"BSC19-024","info_29":null,"info_30":"-","info_31":null,"info_32":null,"info_33":null,"info_34":"-","info_35":null,"info_36":null,"info_37":null,"info_38":null,"info_39":null,"info_40":null,"info_41":"碧奧蘭蒂(植獸形態)","info_42":"LV1・LV2・LV3「這張靈魂卡召喚時」從空間取2個能量至這張靈魂卡上。<br />LV2・LV3「這張靈魂卡攻擊時」對手1張靈魂卡/究極卡變成疲勞狀態。該張靈魂卡/究極卡在下次「對手的回復階段」不能回復。\n","info_43":null,"info_44":null,"info_45":null,"info_46":null,"info_47":null,"info_48":null,"info_49":null,"info_50":null,"delflg":"0","created":"2015-03-11 15:50:54","modified":"2015-03-11 15:50:54","rank":"94233","freewords":"BSC19-024 ビオランテ（植獣形態） スピリット 緑 ［Lv1-Lv2-Lv3］『このスピリットの召喚時』<br />ボイドからコア2個をこのスピリットに置く。 ［Lv2-Lv3］『このスピリットのアタック時』<br />相手のスピリット/アルティメット1体を疲労させる。そのスピリット/アルティメットは次の『相手のリフレッシュステップ』で回復できない。  しょくじゅうけいたい しょうかんじ<br />こ お じ<br />あいて たい ひろう つぎ あいて かいふく  樹魔・古竜 じゅま　こりゅう  ","cost_icon":"<img src='../image/card_serch/icon_green.gif' /><img src='../image/card_serch/icon_green.gif' /><img src='../image/card_serch/icon_green.gif' />","faq":"BSC19-024"},{"id":"94234","character_id":"62","prodid":"62065","subid":"2","info_1":"BSC19-025","info_2":"鎧モスラ","info_3":"スピリット","info_4":"緑","info_5":"9","info_6":"緑4","info_7":"1","info_8":"8000","info_9":"3","info_10":"15000","info_11":null,"info_12":"-","info_13":"M","info_14":"［Lv1-Lv2］『このスピリットのアタック時』<br />BPを比べ相手のスピリットだけを破壊したとき、相手のライフのコア1個を相手のリザーブに置く。","info_15":"［Lv2］『お互いのアタックステップ』<br />カード名に「モスラ」と入っている自分のスピリットがバトルしている間、相手はバーストを発動できない。","info_16":null,"info_17":"一億三千万年の時を経て、レインボーモスラが進化をした姿。<br />全身を覆う鎧のような外骨格はあらゆる攻撃をはね返す強度を誇る。<br />－モスラ3 キングギドラ来襲（1998）－","info_18":null,"info_19":null,"info_20":null,"info_21":"よろい","info_22":"じ<br />くら あいて はかい あいて こ あいて お","info_23":"たが<br />めい はい じぶん あいだ はつどう","info_24":null,"info_25":"怪虫・殻虫","info_26":"かいちゅう　こうちゅう","info_27":"BSC19-025","info_28":"BSC19-025","info_29":null,"info_30":"-","info_31":null,"info_32":null,"info_33":null,"info_34":"-","info_35":null,"info_36":null,"info_37":null,"info_38":null,"info_39":null,"info_40":null,"info_41":"鎧莫斯拉","info_42":"LV1・LV2「這張靈魂卡攻擊時」BP比拼後，只有對手的靈魂卡被破壞時，對手生命值1個能量移至對手的預備區。<br />LV2「雙方的攻擊階段」自己卡名中包含「モスラ」的靈魂卡戰鬥期間，對手不能發動Burst。\n","info_43":null,"info_44":null,"info_45":null,"info_46":null,"info_47":null,"info_48":null,"info_49":null,"info_50":null,"delflg":"0","created":"2015-03-11 15:50:54","modified":"2015-03-11 15:50:54","rank":"94234","freewords":"BSC19-025 鎧モスラ スピリット 緑 ［Lv1-Lv2］『このスピリットのアタック時』<br />BPを比べ相手のスピリットだけを破壊したとき、相手のライフのコア1個を相手のリザーブに置く。 ［Lv2］『お互いのアタックステップ』<br />カード名に「モスラ」と入っている自分のスピリットがバトルしている間、相手はバーストを発動できない。  よろい じ<br />くら あいて はかい あいて こ あいて お たが<br />めい はい じぶん あいだ はつどう  怪虫・殻虫 かいちゅう　こうちゅう  ","cost_icon":"<img src='../image/card_serch/icon_green.gif' /><img src='../image/card_serch/icon_green.gif' /><img src='../image/card_serch/icon_green.gif' /><img src='../image/card_serch/icon_green.gif' />","faq":"BSC19-025"},{"id":"94235","character_id":"62","prodid":"62065","subid":"2","info_1":"BSC19-026","info_2":"バトラ（幼虫）","info_3":"スピリット","info_4":"緑","info_5":"3","info_6":"緑2","info_7":"1","info_8":"3000","info_9":"3","info_10":"5000","info_11":null,"info_12":"-","info_13":"C","info_14":"［Lv1-Lv2］『このスピリットの破壊時』<br />自分の手札/トラッシュにある[バトラ]1枚を、コストを支払わずに召喚できる。","info_15":"［Lv2：フラッシュ］『お互いのアタックステップ』<br />このスピリットを破壊することで、相手のスピリット1体を疲労させる。","info_16":null,"info_17":"対象を破壊する破壊本能のみを持ち合わせている黒い“バトルモスラ”。<br />－ゴジラvsモスラ（1992）－","info_18":null,"info_19":null,"info_20":null,"info_21":"ようちゅう","info_22":"はかいじ<br />じぶん てふだ まい しはら しょうかん","info_23":"たが<br />はかい あいて たい ひろう","info_24":null,"info_25":"刃虫","info_26":"じんちゅう","info_27":"BSC19-026","info_28":"BSC19-026","info_29":null,"info_30":"-","info_31":null,"info_32":null,"info_33":null,"info_34":"-","info_35":null,"info_36":null,"info_37":null,"info_38":null,"info_39":null,"info_40":null,"info_41":"巴特拉(幼蟲)","info_42":"LV1・LV2「這張靈魂卡被破壞時」自己手牌/廢棄區中1張[バトラ]，無需支付需求召喚到場中。<br />LV2：靈動「雙方的攻擊階段」只要破壞這張靈魂卡，對手1張靈魂卡變成疲勞狀態。\n","info_43":null,"info_44":null,"info_45":null,"info_46":null,"info_47":null,"info_48":null,"info_49":null,"info_50":null,"delflg":"0","created":"2015-03-11 15:50:54","modified":"2015-03-11 15:50:54","rank":"94235","freewords":"BSC19-026 バトラ（幼虫） スピリット 緑 ［Lv1-Lv2］『このスピリットの破壊時』<br />自分の手札/トラッシュにある[バトラ]1枚を、コストを支払わずに召喚できる。 ［Lv2：フラッシュ］『お互いのアタックステップ』<br />このスピリットを破壊することで、相手のスピリット1体を疲労させる。  ようちゅう はかいじ<br />じぶん てふだ まい しはら しょうかん たが<br />はかい あいて たい ひろう  刃虫 じんちゅう  ","cost_icon":"<img src='../image/card_serch/icon_green.gif' /><img src='../image/card_serch/icon_green.gif' />","faq":"BSC19-026"},{"id":"94236","character_id":"62","prodid":"62065","subid":"2","info_1":"BSC19-027","info_2":"バトラ","info_3":"スピリット","info_4":"緑・赤","info_5":"7","info_6":"緑2赤2","info_7":"1","info_8":"5000","info_9":"3","info_10":"12000","info_11":null,"info_12":"-","info_13":"M","info_14":"［Lv1-Lv2］『このスピリットのアタック時』<br />BPを比べ相手のスピリットだけを破壊したとき、このスピリットは回復する。","info_15":"［Lv2］『このスピリットのアタック時』<br />このスピリットをBP+5000する。","info_16":null,"info_17":"モスラと激しい決戦を繰り広げる。<br />武器は鋭い爪と翼で発生させる衝撃波、さらに目から発するプリズム光線。<br />－ゴジラvsモスラ（1992）－","info_18":null,"info_19":null,"info_20":null,"info_21":null,"info_22":"じ<br />くら あいて はかい かいふく","info_23":"じ","info_24":null,"info_25":"刃虫","info_26":"じんちゅう","info_27":"BSC19-027","info_28":"BSC19-027","info_29":null,"info_30":"-","info_31":null,"info_32":null,"info_33":null,"info_34":"-","info_35":null,"info_36":null,"info_37":null,"info_38":null,"info_39":null,"info_40":null,"info_41":"巴特拉","info_42":"LV1・LV2「這張靈魂卡攻擊時」BP比拼後只有對手的靈魂卡被破壞時，這張靈魂卡變成回復狀態。<br />LV2「這張靈魂卡攻擊時」這張靈魂卡 +5000BP。\n","info_43":null,"info_44":null,"info_45":null,"info_46":null,"info_47":null,"info_48":null,"info_49":null,"info_50":null,"delflg":"0","created":"2015-03-11 15:50:54","modified":"2015-03-11 15:50:54","rank":"94236","freewords":"BSC19-027 バトラ スピリット 緑・赤 ［Lv1-Lv2］『このスピリットのアタック時』<br />BPを比べ相手のスピリットだけを破壊したとき、このスピリットは回復する。 ［Lv2］『このスピリットのアタック時』<br />このスピリットをBP+5000する。   じ<br />くら あいて はかい かいふく じ  刃虫 じんちゅう  ","cost_icon":"<img src='../image/card_serch/icon_green.gif' /><img src='../image/card_serch/icon_green.gif' /><img src='../image/card_serch/icon_red.gif' /><img src='../image/card_serch/icon_red.gif' />","faq":"BSC19-027"},{"id":"94237","character_id":"62","prodid":"62065","subid":"2","info_1":"BSC19-028","info_2":"ランドモゲラー","info_3":"スピリット","info_4":"白","info_5":"1","info_6":"白1","info_7":"1","info_8":"2000","info_9":"2","info_10":"4000","info_11":"4","info_12":"6000","info_13":"C","info_14":null,"info_15":null,"info_16":null,"info_17":"MOGERAの上半身部を構成する地底戦車。<br />中央のバスタードリルと両サイドの自動追尾レーザー砲で、<br />地中を高速で掘り進む。　－ゴジラvsスペースゴジラ（1994）－","info_18":null,"info_19":null,"info_20":null,"info_21":null,"info_22":null,"info_23":null,"info_24":null,"info_25":"動器","info_26":"どうき","info_27":"BSC19-028","info_28":"BSC19-028","info_29":null,"info_30":"-","info_31":null,"info_32":null,"info_33":null,"info_34":"-","info_35":null,"info_36":null,"info_37":null,"info_38":null,"info_39":null,"info_40":null,"info_41":"大地摩傑拉","info_42":"\n","info_43":null,"info_44":null,"info_45":null,"info_46":null,"info_47":null,"info_48":null,"info_49":null,"info_50":null,"delflg":"0","created":"2015-03-11 15:50:54","modified":"2015-03-11 15:50:54","rank":"94237","freewords":"BSC19-028 ランドモゲラー スピリット 白        動器 どうき  ","cost_icon":"<img src='../image/card_serch/icon_white.gif' />","faq":"沒有"},{"id":"94238","character_id":"62","prodid":"62065","subid":"2","info_1":"BSC19-029","info_2":"スターファルコン","info_3":"スピリット","info_4":"白","info_5":"2","info_6":"白2","info_7":"1","info_8":"4000","info_9":"2","info_10":"6000","info_11":"4","info_12":"8000","info_13":"C","info_14":null,"info_15":null,"info_16":null,"info_17":"MOGERAの下半身部を構成する高性能戦闘機。<br />省電力メーサーバルカン砲を主武器に空中戦を展開する。<br />－ゴジラvsスペースゴジラ（1994）－","info_18":null,"info_19":null,"info_20":null,"info_21":null,"info_22":null,"info_23":null,"info_24":null,"info_25":"動器","info_26":"どうき","info_27":"BSC19-029","info_28":"BSC19-029","info_29":null,"info_30":"-","info_31":null,"info_32":null,"info_33":null,"info_34":"-","info_35":null,"info_36":null,"info_37":null,"info_38":null,"info_39":null,"info_40":null,"info_41":"星際飛鷹","info_42":"\n","info_43":null,"info_44":null,"info_45":null,"info_46":null,"info_47":null,"info_48":null,"info_49":null,"info_50":null,"delflg":"0","created":"2015-03-11 15:50:54","modified":"2015-03-11 15:50:54","rank":"94238","freewords":"BSC19-029 スターファルコン スピリット 白        動器 どうき  ","cost_icon":"<img src='../image/card_serch/icon_white.gif' /><img src='../image/card_serch/icon_white.gif' />","faq":"沒有"},{"id":"94239","character_id":"62","prodid":"62065","subid":"2","info_1":"BSC19-030","info_2":"スーパーＸIII","info_3":"スピリット","info_4":"白","info_5":"3","info_6":"白2","info_7":"1","info_8":"3000","info_9":"3","info_10":"6000","info_11":null,"info_12":"-","info_13":"C","info_14":"［Lv1-Lv2］『このスピリットの召喚時』<br />相手のネクサス1つを手札に戻す。","info_15":"［Lv2］『このスピリットのアタック時』<br />相手の赤のスピリット1体を手札に戻す。","info_16":null,"info_17":"搭載されたすべての兵器が冷凍兵器。<br />超低温レーザー砲はターゲットをマイナス200度まで瞬間冷凍できる。<br />－ゴジラvsデストロイア（1995）－","info_18":null,"info_19":null,"info_20":null,"info_21":"エックススリー","info_22":"しょうかんじ<br />あいて てふだ もど","info_23":"じ<br />あいて あか てふだ もど","info_24":null,"info_25":"動器","info_26":"どうき","info_27":"BSC19-030","info_28":"BSC19-030","info_29":null,"info_30":"-","info_31":null,"info_32":null,"info_33":null,"info_34":"-","info_35":null,"info_36":null,"info_37":null,"info_38":null,"info_39":null,"info_40":null,"info_41":"超級XIII","info_42":"LV1・LV2「這張靈魂卡召喚時」對手1張核心卡回到手牌。<br />LV2「這張靈魂卡攻擊時」對手1張紅色靈魂卡回到手牌。\n","info_43":null,"info_44":null,"info_45":null,"info_46":null,"info_47":null,"info_48":null,"info_49":null,"info_50":null,"delflg":"0","created":"2015-03-11 15:50:54","modified":"2015-03-11 15:50:54","rank":"94239","freewords":"BSC19-030 スーパーＸIII スピリット 白 ［Lv1-Lv2］『このスピリットの召喚時』<br />相手のネクサス1つを手札に戻す。 ［Lv2］『このスピリットのアタック時』<br />相手の赤のスピリット1体を手札に戻す。  エックススリー しょうかんじ<br />あいて てふだ もど じ<br />あいて あか てふだ もど  動器 どうき  ","cost_icon":"<img src='../image/card_serch/icon_white.gif' /><img src='../image/card_serch/icon_white.gif' />","faq":"沒有"},{"id":"94240","character_id":"62","prodid":"62065","subid":"2","info_1":"BSC19-031","info_2":"MOGERA","info_3":"スピリット","info_4":"白","info_5":"3","info_6":"白3","info_7":"1","info_8":"3000","info_9":"2","info_10":"5000","info_11":null,"info_12":"-","info_13":"U","info_14":"［Lv1-Lv2］『相手のアタックステップ』<br />自分の[ランドモゲラー]か[スターファルコン]1体につき、このスピリットをBP+2000する。","info_15":"［Lv2］『自分のエンドステップ』<br />自分の[ランドモゲラー]か[スターファルコン]がいるとき、このスピリットは回復する。","info_16":null,"info_17":"メーサーキャノン、スパイラルグレネードミサイルを武器に闘う、対ゴジラ兵器。<br />戦車・ランドモゲラーと戦闘機・スターファルコンが合体してロボット形態となる。<br />－ゴジラvsスペースゴジラ（1994）－","info_18":null,"info_19":null,"info_20":null,"info_21":"モゲラ","info_22":"あいて<br />じぶん まい たい","info_23":"じぶん<br />じぶん かいふく","info_24":null,"info_25":"武装","info_26":"ぶそう","info_27":"BSC19-031","info_28":"BSC19-031","info_29":null,"info_30":"-","info_31":null,"info_32":null,"info_33":null,"info_34":"-","info_35":null,"info_36":null,"info_37":null,"info_38":null,"info_39":null,"info_40":null,"info_41":"MOGERA","info_42":"LV1・LV2「對手的攻擊階段」自己每有1張[ランドモゲラー]或[スターファルコン]，這張靈魂卡 +2000BP。<br />LV2「自己的結束階段」自分有[ランドモゲラー]或[スターファルコン]時，這張靈魂卡變成回復狀態。\n","info_43":null,"info_44":null,"info_45":null,"info_46":null,"info_47":null,"info_48":null,"info_49":null,"info_50":null,"delflg":"0","created":"2015-03-11 15:50:54","modified":"2015-03-11 15:50:54","rank":"94240","freewords":"BSC19-031 MOGERA スピリット 白 ［Lv1-Lv2］『相手のアタックステップ』<br />自分の[ランドモゲラー]か[スターファルコン]1体につき、このスピリットをBP+2000する。 ［Lv2］『自分のエンドステップ』<br />自分の[ランドモゲラー]か[スターファルコン]がいるとき、このスピリットは回復する。  モゲラ あいて<br />じぶん まい たい じぶん<br />じぶん かいふく  武装 ぶそう  ","cost_icon":"<img src='../image/card_serch/icon_white.gif' /><img src='../image/card_serch/icon_white.gif' /><img src='../image/card_serch/icon_white.gif' />","faq":"沒有"},{"id":"94241","character_id":"62","prodid":"62065","subid":"2","info_1":"BSC19-032","info_2":"メカゴジラ［1974］","info_3":"スピリット","info_4":"白","info_5":"4","info_6":"白2","info_7":"1","info_8":"3000","info_9":"2","info_10":"5000","info_11":null,"info_12":"-","info_13":"C","info_14":"［Lv1-Lv2］『このスピリットの召喚時』<br />相手のスピリット1体を手札に戻す。","info_15":"［Lv2］【超装甲：赤】<br />このスピリットは、相手の赤のスピリット/アルティメット/ネクサス/マジックの効果を受けない。","info_16":null,"info_17":"ゴジラを分析して作られたサイボーグ怪獣。<br />指からミサイルを発射し、鼻から火炎弾を発射して戦う。<br />守りは眼からビームを発しながら頭部が回転してバリヤーを張る。<br />-ゴジラ対メカゴジラ（1974）-","info_18":null,"info_19":null,"info_20":null,"info_21":null,"info_22":"しょうかんじ<br />あいて たい てふだ もど","info_23":"ちょうそうこう あか<br />あいて あか こうか う","info_24":null,"info_25":"機獣","info_26":"きじゅう","info_27":"BSC19-032","info_28":"BSC19-032","info_29":null,"info_30":"-","info_31":null,"info_32":null,"info_33":null,"info_34":"-","info_35":null,"info_36":null,"info_37":null,"info_38":null,"info_39":null,"info_40":null,"info_41":"機械哥斯拉[1974]","info_42":"Lv1・Lv2「這張靈魂卡召喚時」對手1張靈魂卡回到手牌。<br />LV2【超裝甲：紅色】這張靈魂卡不受對手紅色的靈魂卡/究極卡/核心卡/魔法卡效果所影響。\n","info_43":null,"info_44":null,"info_45":null,"info_46":null,"info_47":null,"info_48":null,"info_49":null,"info_50":null,"delflg":"0","created":"2015-03-11 15:50:54","modified":"2015-03-11 15:50:54","rank":"94241","freewords":"BSC19-032 メカゴジラ［1974］ スピリット 白 ［Lv1-Lv2］『このスピリットの召喚時』<br />相手のスピリット1体を手札に戻す。 ［Lv2］【超装甲：赤】<br />このスピリットは、相手の赤のスピリット/アルティメット/ネクサス/マジックの効果を受けない。   しょうかんじ<br />あいて たい てふだ もど ちょうそうこう あか<br />あいて あか こうか う  機獣 きじゅう  ","cost_icon":"<img src='../image/card_serch/icon_white.gif' /><img src='../image/card_serch/icon_white.gif' />","faq":"BSC19-032"},{"id":"94242","character_id":"62","prodid":"62065","subid":"2","info_1":"BSC19-033","info_2":"ジェット・ジャガー［1973］","info_3":"スピリット","info_4":"白","info_5":"4","info_6":"白3","info_7":"1","info_8":"4000","info_9":"2","info_10":"5000","info_11":"3","info_12":"7000","info_13":"U","info_14":null,"info_15":"［Lv2］『このスピリットのブロック時』<br />BP5000以下の相手のスピリット1体を疲労させる。","info_16":"［Lv3］『このスピリットのブロック時』<br />相手のスピリット1体を疲労させる。","info_17":"精密コンピューターが内蔵され自らの意志で戦うロボット。<br />全身は鋼のように固く、空手チョップ一撃でビルを真っ二つにする。<br />-ゴジラ対メガロ（1973）-","info_18":null,"info_19":null,"info_20":null,"info_21":null,"info_22":null,"info_23":"じ<br />いか あいて たい ひろう","info_24":"じ<br />あいて たい ひろう","info_25":"武装","info_26":"ぶそう","info_27":"BSC19-033","info_28":"BSC19-033","info_29":null,"info_30":"-","info_31":null,"info_32":null,"info_33":null,"info_34":"-","info_35":null,"info_36":null,"info_37":null,"info_38":null,"info_39":null,"info_40":null,"info_41":"噴射積格[1973]","info_42":"LV2「這張靈魂卡防禦時」對手1張BP5000或以下的靈魂卡變成疲勞狀態。<br />LV3「這張靈魂卡防禦時」對手1張靈魂卡變成疲勞狀態。\n","info_43":null,"info_44":null,"info_45":null,"info_46":null,"info_47":null,"info_48":null,"info_49":null,"info_50":null,"delflg":"0","created":"2015-03-11 15:50:54","modified":"2015-03-11 15:50:54","rank":"94242","freewords":"BSC19-033 ジェット・ジャガー［1973］ スピリット 白  ［Lv2］『このスピリットのブロック時』<br />BP5000以下の相手のスピリット1体を疲労させる。 ［Lv3］『このスピリットのブロック時』<br />相手のスピリット1体を疲労させる。   じ<br />いか あいて たい ひろう じ<br />あいて たい ひろう 武装 ぶそう  ","cost_icon":"<img src='../image/card_serch/icon_white.gif' /><img src='../image/card_serch/icon_white.gif' /><img src='../image/card_serch/icon_white.gif' />","faq":"沒有"},{"id":"94243","character_id":"62","prodid":"62065","subid":"2","info_1":"BSC19-034","info_2":"新轟天号","info_3":"スピリット","info_4":"白","info_5":"5","info_6":"白2","info_7":"1","info_8":"4000","info_9":"2","info_10":"6000","info_11":null,"info_12":"-","info_13":"R","info_14":"［Lv1-Lv2］『自分のエンドステップ』<br />このスピリットは回復する。","info_15":"［Lv2］『このスピリットのアタック時』<br />自分のライフが2以下のとき、このスピリットは相手のスピリットからブロックされない。","info_16":null,"info_17":"地球防衛軍の戦艦。<br />海中・空中での戦闘が可能。頭部のドリル・冷凍メーサー砲を武器に闘う。<br />－ゴジラ FINALWARS（2004）－","info_18":null,"info_19":null,"info_20":null,"info_21":"しんごうてんごう","info_22":"じぶん<br />かいふく","info_23":"じ<br />じぶん いか あいて","info_24":null,"info_25":"動器","info_26":"どうき","info_27":"BSC19-034","info_28":"BSC19-034","info_29":null,"info_30":"-","info_31":null,"info_32":null,"info_33":null,"info_34":"-","info_35":null,"info_36":null,"info_37":null,"info_38":null,"info_39":null,"info_40":null,"info_41":"新轟天號","info_42":"LV1・LV2「自己的結束階段」這張靈魂卡變成回復狀態。<br />LV2「這張靈魂卡攻擊時」自己的生命值2個或以下時，這張靈魂卡不會被對手所防禦。\n","info_43":null,"info_44":null,"info_45":null,"info_46":null,"info_47":null,"info_48":null,"info_49":null,"info_50":null,"delflg":"0","created":"2015-03-11 15:50:54","modified":"2015-03-11 15:50:54","rank":"94243","freewords":"BSC19-034 新轟天号 スピリット 白 ［Lv1-Lv2］『自分のエンドステップ』<br />このスピリットは回復する。 ［Lv2］『このスピリットのアタック時』<br />自分のライフが2以下のとき、このスピリットは相手のスピリットからブロックされない。  しんごうてんごう じぶん<br />かいふく じ<br />じぶん いか あいて  動器 どうき  ","cost_icon":"<img src='../image/card_serch/icon_white.gif' /><img src='../image/card_serch/icon_white.gif' />","faq":"沒有"},{"id":"94244","character_id":"62","prodid":"62065","subid":"2","info_1":"BSC19-035","info_2":"メカゴジラ[1993]","info_3":"スピリット","info_4":"白","info_5":"5","info_6":"白3","info_7":"1","info_8":"4000","info_9":"2","info_10":"6000","info_11":"4","info_12":"9000","info_13":"R","info_14":"［Lv1-Lv2-Lv3］【超装甲：赤/白】<br />このスピリットは、相手の赤/白のスピリット/アルティメット/ネクサス/マジックの効果を受けない。<br />［Lv1-Lv2-Lv3］『このスピリットのアタック時』<br />このスピリットのBP以下の相手のスピリット1体を手札に戻す。","info_15":"《合体時》［Lv2-Lv3］『相手のアタックステップ』<br />このスピリットは疲労状態でブロックできる。","info_16":null,"info_17":"23世紀のテクノロジーを駆使して作られた最強バトルマシン。<br />－ゴジラvsメカゴジラ（1993）－","info_18":null,"info_19":null,"info_20":null,"info_21":null,"info_22":"ちょうそうこう あか しろ<br />あいて あか しろ こうか う<br />じ<br />いか あいて たい てふだ もど","info_23":"ブレイヴじ あいて<br />ひろうじょうたい","info_24":null,"info_25":"機獣","info_26":"きじゅう","info_27":"BSC19-035","info_28":"BSC19-035","info_29":null,"info_30":"-","info_31":null,"info_32":null,"info_33":null,"info_34":"-","info_35":null,"info_36":null,"info_37":null,"info_38":null,"info_39":null,"info_40":null,"info_41":"機械哥斯拉[1993]","info_42":"LV1・LV2・LV3【超裝甲：紅/白】<br />這張靈魂卡/究極卡不受對手紅/白色的靈魂卡/究極卡/核心卡/魔法卡效果影響。<br />LV1・LV2・LV3「這張靈魂卡攻擊時」對手1張BP比這張靈魂卡低或相同的靈魂卡回到手牌。<br />【合體時】LV2・LV3「對手的攻擊階段」這張靈魂卡可以疲勞狀態進行防禦。\n","info_43":null,"info_44":null,"info_45":null,"info_46":null,"info_47":null,"info_48":null,"info_49":null,"info_50":null,"delflg":"0","created":"2015-03-11 15:50:54","modified":"2015-03-11 15:50:54","rank":"94244","freewords":"BSC19-035 メカゴジラ[1993] スピリット 白 ［Lv1-Lv2-Lv3］【超装甲：赤/白】<br />このスピリットは、相手の赤/白のスピリット/アルティメット/ネクサス/マジックの効果を受けない。<br />［Lv1-Lv2-Lv3］『このスピリットのアタック時』<br />このスピリットのBP以下の相手のスピリット1体を手札に戻す。 《合体時》［Lv2-Lv3］『相手のアタックステップ』<br />このスピリットは疲労状態でブロックできる。   ちょうそうこう あか しろ<br />あいて あか しろ こうか う<br />じ<br />いか あいて たい てふだ もど ブレイヴじ あいて<br />ひろうじょうたい  機獣 きじゅう  ","cost_icon":"<img src='../image/card_serch/icon_white.gif' /><img src='../image/card_serch/icon_white.gif' /><img src='../image/card_serch/icon_white.gif' />","faq":"BSC19-035"},{"id":"94245","character_id":"62","prodid":"62065","subid":"2","info_1":"BSC19-036","info_2":"改造ガイガン［2004］","info_3":"スピリット","info_4":"白","info_5":"5","info_6":"白2赤1","info_7":"1","info_8":"5000","info_9":"2","info_10":"7000","info_11":"4","info_12":"9000","info_13":"U","info_14":null,"info_15":"［Lv2-Lv3］『このスピリットのアタック時』<br />BP5000以下の相手のスピリット2体を手札に戻す。","info_16":null,"info_17":"ガイガンが強化改造をされた姿。<br />両腕はチェインソーに換装されより凶悪になった。<br />－ゴジラ FINALWARS（2004）－","info_18":null,"info_19":null,"info_20":null,"info_21":"かいぞう","info_22":null,"info_23":"じ<br />いか あいて たい てふだ もど","info_24":null,"info_25":"甲竜・星竜","info_26":"こうりゅう　せいりゅう","info_27":"BSC19-036","info_28":"BSC19-036","info_29":null,"info_30":"-","info_31":null,"info_32":null,"info_33":null,"info_34":"-","info_35":null,"info_36":null,"info_37":null,"info_38":null,"info_39":null,"info_40":null,"info_41":"改造蓋剛[2004]","info_42":"LV2・LV3「這張靈魂卡攻擊時」對手2張BP5000或以下的靈魂卡回到手牌。\n","info_43":null,"info_44":null,"info_45":null,"info_46":null,"info_47":null,"info_48":null,"info_49":null,"info_50":null,"delflg":"0","created":"2015-03-11 15:50:54","modified":"2015-03-11 15:50:54","rank":"94245","freewords":"BSC19-036 改造ガイガン［2004］ スピリット 白  ［Lv2-Lv3］『このスピリットのアタック時』<br />BP5000以下の相手のスピリット2体を手札に戻す。  かいぞう  じ<br />いか あいて たい てふだ もど  甲竜・星竜 こうりゅう　せいりゅう  ","cost_icon":"<img src='../image/card_serch/icon_white.gif' /><img src='../image/card_serch/icon_white.gif' /><img src='../image/card_serch/icon_red.gif' />","faq":"沒有"},{"id":"94246","character_id":"62","prodid":"62065","subid":"2","info_1":"BSC19-037","info_2":"3式機龍","info_3":"スピリット","info_4":"白","info_5":"6","info_6":"白3","info_7":"1","info_8":"5000","info_9":"2","info_10":"7000","info_11":"4","info_12":"10000","info_13":"M","info_14":"［Lv1-Lv2-Lv3］『このスピリットの召喚時』<br />相手のスピリット/アルティメット1体を手札に戻す。<br />［Lv1-Lv2-Lv3］【超装甲：赤/緑】<br />このスピリットは、相手の赤/緑のスピリット/アルティメット/ネクサス/マジックの効果を受けない。","info_15":"［Lv2-Lv3］<br />相手の赤のスピリットがいる間、このスピリットをBP+10000する。","info_16":null,"info_17":"初代ゴジラの骨をベースに作られた、生体ロボット。<br />－ゴジラＸメカゴジラ（2002）－","info_18":null,"info_19":null,"info_20":null,"info_21":"しききりゅう","info_22":"しょうかんじ<br />あいて たい てふだ もど<br />ちょうそうこう あか みどり<br />あいて あか みどり こうか う","info_23":"あいて あか あいだ","info_24":null,"info_25":"機獣","info_26":"きじゅう","info_27":"BSC19-037","info_28":"BSC19-037","info_29":null,"info_30":"-","info_31":null,"info_32":null,"info_33":null,"info_34":"-","info_35":null,"info_36":null,"info_37":null,"info_38":null,"info_39":null,"info_40":null,"info_41":"3式機龍","info_42":"LV1・LV2・LV3「這張靈魂卡召喚時」對手1張靈魂卡/究極卡回到手牌。<br />LV1・LV2・LV3【超裝甲：紅/綠】<br />這張靈魂卡/究極卡不受對手紅/綠色的靈魂卡/究極卡/核心卡/魔法卡效果影響。<br />LV2・LV3 對手有紅色靈魂卡期間，這張靈魂卡 +1000BP。\n","info_43":null,"info_44":null,"info_45":null,"info_46":null,"info_47":null,"info_48":null,"info_49":null,"info_50":null,"delflg":"0","created":"2015-03-11 15:50:54","modified":"2015-03-11 15:50:54","rank":"94246","freewords":"BSC19-037 3式機龍 スピリット 白 ［Lv1-Lv2-Lv3］『このスピリットの召喚時』<br />相手のスピリット/アルティメット1体を手札に戻す。<br />［Lv1-Lv2-Lv3］【超装甲：赤/緑】<br />このスピリットは、相手の赤/緑のスピリット/アルティメット/ネクサス/マジックの効果を受けない。 ［Lv2-Lv3］<br />相手の赤のスピリットがいる間、このスピリットをBP+10000する。  しききりゅう しょうかんじ<br />あいて たい てふだ もど<br />ちょうそうこう あか みどり<br />あいて あか みどり こうか う あいて あか あいだ  機獣 きじゅう  ","cost_icon":"<img src='../image/card_serch/icon_white.gif' /><img src='../image/card_serch/icon_white.gif' /><img src='../image/card_serch/icon_white.gif' />","faq":"BSC19-037"},{"id":"94247","character_id":"62","prodid":"62065","subid":"2","info_1":"BSC19-038","info_2":"メカキングギドラ","info_3":"スピリット","info_4":"白","info_5":"8","info_6":"白3赤1","info_7":"1","info_8":"6000","info_9":"2","info_10":"10000","info_11":"4","info_12":"13000","info_13":"R","info_14":"［Lv1-Lv2-Lv3］『このスピリットの召喚時』<br />相手のスピリット3体を手札に戻す。","info_15":null,"info_16":null,"info_17":"ゴジラとの戦いで首を1本失ったキングギドラが、<br />未来の技術でサイボーグ化され復活した姿。<br />-ゴジラvsキングギドラ（1991）-","info_18":null,"info_19":null,"info_20":null,"info_21":null,"info_22":"しょうかんじ<br />あいて たい てふだ もど","info_23":null,"info_24":null,"info_25":"甲竜・星竜","info_26":"こうりゅう　せいりゅう","info_27":"BSC19-038","info_28":"BSC19-038","info_29":null,"info_30":"-","info_31":null,"info_32":null,"info_33":null,"info_34":"-","info_35":null,"info_36":null,"info_37":null,"info_38":null,"info_39":null,"info_40":null,"info_41":"機械王者基多拉","info_42":"LV1・LV2・LV3「這張靈魂卡召喚時」對手3張靈魂卡回到手牌。\n","info_43":null,"info_44":null,"info_45":null,"info_46":null,"info_47":null,"info_48":null,"info_49":null,"info_50":null,"delflg":"0","created":"2015-03-11 15:50:55","modified":"2015-03-11 15:50:55","rank":"94247","freewords":"BSC19-038 メカキングギドラ スピリット 白 ［Lv1-Lv2-Lv3］『このスピリットの召喚時』<br />相手のスピリット3体を手札に戻す。    しょうかんじ<br />あいて たい てふだ もど   甲竜・星竜 こうりゅう　せいりゅう  ","cost_icon":"<img src='../image/card_serch/icon_white.gif' /><img src='../image/card_serch/icon_white.gif' /><img src='../image/card_serch/icon_white.gif' /><img src='../image/card_serch/icon_red.gif' />","faq":"沒有"},{"id":"94253","character_id":"62","prodid":"62065","subid":"2","info_1":"BSC19-039","info_2":"ガルーダ","info_3":"ブレイヴ","info_4":"白","info_5":"5","info_6":"白3","info_7":"1","info_8":"4000","info_9":null,"info_10":"-","info_11":"合体","info_12":"+4000","info_13":"C","info_14":"カード名に「メカゴジラ」と入っている自分のスピリットがいる間、手札にあるこのブレイヴカードを召喚するとき、コスト3として扱う。","info_15":"《合体条件：コスト4以上》","info_16":"《合体時》『このスピリットのブロック時』<br />このスピリットをBP+3000し、ボイドからコア1個をこのスピリットに置く。","info_17":"対Ｇ兵器の試作1号機として作ったマシン。<br />メカゴジラと合体することでスーパーメカゴジラとなり、<br />機動力と攻撃力が大幅にアップする。　－ゴジラvsメカゴジラ（1993）－","info_18":null,"info_19":null,"info_20":null,"info_21":null,"info_22":"めい　はい じぶん あいだ てふだ しょうかん あつか","info_23":"ブレイヴじょうけん　いじょう","info_24":"ブレイヴじ じ<br />こ お","info_25":"動器","info_26":"どうき","info_27":"BSC19-039","info_28":"BSC19-039","info_29":null,"info_30":"-","info_31":null,"info_32":null,"info_33":null,"info_34":"-","info_35":null,"info_36":null,"info_37":null,"info_38":null,"info_39":null,"info_40":null,"info_41":"加路達","info_42":"自己有卡名中包含「メカゴジラ」的靈魂卡期間，召喚手牌中的這張Brave時，當作需求 3使用。<br />合體條件：需求4或以上<br />【合體時】「這張靈魂卡防禦時」這張靈魂卡 +3000BP，從空間取1個能量至這張靈魂卡上。\n","info_43":null,"info_44":null,"info_45":null,"info_46":null,"info_47":null,"info_48":null,"info_49":null,"info_50":null,"delflg":"0","created":"2015-03-11 15:50:55","modified":"2015-03-11 15:50:55","rank":"94253","freewords":"BSC19-039 ガルーダ ブレイヴ 白 カード名に「メカゴジラ」と入っている自分のスピリットがいる間、手札にあるこのブレイヴカードを召喚するとき、コスト3として扱う。 《合体条件：コスト4以上》 《合体時》『このスピリットのブロック時』<br />このスピリットをBP+3000し、ボイドからコア1個をこのスピリットに置く。  めい　はい じぶん あいだ てふだ しょうかん あつか ブレイヴじょうけん　いじょう ブレイヴじ じ<br />こ お 動器 どうき  ","cost_icon":"<img src='../image/card_serch/icon_white.gif' /><img src='../image/card_serch/icon_white.gif' /><img src='../image/card_serch/icon_white.gif' />","faq":"BSC19-039"},{"id":"94254","character_id":"62","prodid":"62065","subid":"2","info_1":"BSC19-040","info_2":"結晶地帯","info_3":"ネクサス","info_4":"赤","info_5":"3","info_6":"赤1","info_7":"-","info_8":"-","info_9":"3","info_10":"-","info_11":null,"info_12":"-","info_13":"U","info_14":"自分の[スペースゴジラ]がいる間、手札にあるこのネクサスカードを配置するとき、コスト1として扱う。<br />［Lv1-Lv2］<br />カード名に「ゴジラ」と入っている自分のスピリットすべてを、そのスピリットが持つ最高Lvとして扱う。","info_15":"［Lv2］『自分のドローステップ』<br />ドローの枚数を+1枚する。","info_16":null,"info_17":"スペースゴジラが結晶体を使い、<br />無限に宇宙エネルギーを受信するエリアを作り上げた。<br />－ゴジラvsスペースゴジラ（1994）－","info_18":null,"info_19":null,"info_20":null,"info_21":"けっしょうちたい","info_22":"じぶん あいだ てふだ はいち あつか<br />めい はい　じぶん も さいこう あつか","info_23":"じぶん<br />まいすう まい","info_24":null,"info_25":"-","info_26":null,"info_27":"BSC19-040","info_28":"BSC19-040","info_29":null,"info_30":"-","info_31":null,"info_32":null,"info_33":null,"info_34":"-","info_35":null,"info_36":null,"info_37":null,"info_38":null,"info_39":null,"info_40":null,"info_41":"結晶地帶","info_42":"自己有[スペースゴジラ]期間，配置手牌中這張核心卡時，當作需求 1。<br />LV1・LV2<br />自己全部卡名中包含「ゴジラ」的靈魂卡，當作該靈魂卡的最高LV使用。<br />LV2「自己的抽牌階段」抽牌數目+1。\n","info_43":null,"info_44":null,"info_45":null,"info_46":null,"info_47":null,"info_48":null,"info_49":null,"info_50":null,"delflg":"0","created":"2015-03-11 15:50:55","modified":"2015-03-11 15:50:55","rank":"94254","freewords":"BSC19-040 結晶地帯 ネクサス 赤 自分の[スペースゴジラ]がいる間、手札にあるこのネクサスカードを配置するとき、コスト1として扱う。<br />［Lv1-Lv2］<br />カード名に「ゴジラ」と入っている自分のスピリットすべてを、そのスピリットが持つ最高Lvとして扱う。 ［Lv2］『自分のドローステップ』<br />ドローの枚数を+1枚する。  けっしょうちたい じぶん あいだ てふだ はいち あつか<br />めい はい　じぶん も さいこう あつか じぶん<br />まいすう まい     ","cost_icon":"<img src='../image/card_serch/icon_red.gif' />","faq":"BSC19-040"},{"id":"94255","character_id":"62","prodid":"62065","subid":"2","info_1":"BSC19-041","info_2":"妖星ゴラス","info_3":"ネクサス","info_4":"赤","info_5":"4","info_6":"赤2","info_7":"-","info_8":"-","info_9":"1","info_10":"-","info_11":null,"info_12":"-","info_13":"U","info_14":"［Lv1-Lv2］『このネクサスの配置時』<br />自分のデッキを上から5枚オープンできる。その中の[カイザーギドラ]と[モンスターＸ]すべてを手札に加える。残ったカードは破棄する。","info_15":"［Lv2］『自分のアタックステップ』<br />自分の赤のスピリットすべてをBP+3000する。","info_16":null,"info_17":"地球に向かって進行をする、謎の燃える妖星。<br />－ゴジラ FINALWARS（2004）－","info_18":null,"info_19":null,"info_20":null,"info_21":"ようせい","info_22":"はいちじ<br />じぶん うえ まい なか エックス てふだ くわ のこ はき","info_23":"じぶん<br />じぶん あか","info_24":null,"info_25":"-","info_26":null,"info_27":"BSC19-041","info_28":"BSC19-041","info_29":null,"info_30":"-","info_31":null,"info_32":null,"info_33":null,"info_34":"-","info_35":null,"info_36":null,"info_37":null,"info_38":null,"info_39":null,"info_40":null,"info_41":"妖星哥拉斯","info_42":"LV1・LV2「這張核心卡配置時」可從自己牌組上公開5張卡牌。把當中的[カイザーギドラ]及[モンスターX]全部加進手牌。捨棄餘下的卡牌。<br />LV2「自己的攻擊階段」自己全部紅色的靈魂卡 +3000BP。\n","info_43":null,"info_44":null,"info_45":null,"info_46":null,"info_47":null,"info_48":null,"info_49":null,"info_50":null,"delflg":"0","created":"2015-03-11 15:50:55","modified":"2015-03-11 15:50:55","rank":"94255","freewords":"BSC19-041 妖星ゴラス ネクサス 赤 ［Lv1-Lv2］『このネクサスの配置時』<br />自分のデッキを上から5枚オープンできる。その中の[カイザーギドラ]と[モンスターＸ]すべてを手札に加える。残ったカードは破棄する。 ［Lv2］『自分のアタックステップ』<br />自分の赤のスピリットすべてをBP+3000する。  ようせい はいちじ<br />じぶん うえ まい なか エックス てふだ くわ のこ はき じぶん<br />じぶん あか     ","cost_icon":"<img src='../image/card_serch/icon_red.gif' /><img src='../image/card_serch/icon_red.gif' />","faq":"BSC19-041"},{"id":"94256","character_id":"62","prodid":"62065","subid":"2","info_1":"BSC19-042","info_2":"目覚めの時","info_3":"ネクサス","info_4":"緑","info_5":"3","info_6":"緑2","info_7":"-","info_8":"-","info_9":"1","info_10":"-","info_11":null,"info_12":"-","info_13":"U","info_14":"［Lv1-Lv2］<br />カード名に「モスラ」と入っている自分のスピリットが破壊されたとき、ボイドからコア1個を自分のリザーブに置く。","info_15":"［Lv2］『相手のアタックステップ』<br />自分のライフが減ったとき、減ったライフのコア1個につき、自分はデッキから1枚ドローする。","info_16":null,"info_17":"小美人を追って東京に来たインファント島の守り神モスラは、<br />タワーをへし折り、糸を吐きながら巨大な繭を作った。<br />－モスラ（1961）－","info_18":null,"info_19":null,"info_20":null,"info_21":"めざ とき","info_22":"めい はい じぶん はかい こ じぶん お","info_23":"あいて<br />じぶん へ へ こ じぶん まい","info_24":null,"info_25":"-","info_26":null,"info_27":"BSC19-042","info_28":"BSC19-042","info_29":null,"info_30":"-","info_31":null,"info_32":null,"info_33":null,"info_34":"-","info_35":null,"info_36":null,"info_37":null,"info_38":null,"info_39":null,"info_40":null,"info_41":"甦醒之時","info_42":"LV1・LV2 自己卡名中包含「モスラ」的靈魂卡被破壞時，從空間取1個能量至自己的預備區。<br />LV2「對手的攻擊階段」自己生命值被削減時，每減少1個生命值的能量，就從自己牌組抽1張牌。\n","info_43":null,"info_44":null,"info_45":null,"info_46":null,"info_47":null,"info_48":null,"info_49":null,"info_50":null,"delflg":"0","created":"2015-03-11 15:50:55","modified":"2015-03-11 15:50:55","rank":"94256","freewords":"BSC19-042 目覚めの時 ネクサス 緑 ［Lv1-Lv2］<br />カード名に「モスラ」と入っている自分のスピリットが破壊されたとき、ボイドからコア1個を自分のリザーブに置く。 ［Lv2］『相手のアタックステップ』<br />自分のライフが減ったとき、減ったライフのコア1個につき、自分はデッキから1枚ドローする。  めざ とき めい はい じぶん はかい こ じぶん お あいて<br />じぶん へ へ こ じぶん まい     ","cost_icon":"<img src='../image/card_serch/icon_green.gif' /><img src='../image/card_serch/icon_green.gif' />","faq":"BSC19-042"},{"id":"94257","character_id":"62","prodid":"62065","subid":"2","info_1":"BSC19-043","info_2":"インファント島","info_3":"ネクサス","info_4":"緑","info_5":"4","info_6":"緑2","info_7":"-","info_8":"-","info_9":"1","info_10":"-","info_11":null,"info_12":"-","info_13":"C","info_14":"［Lv1-Lv2］『このネクサスの配置時』<br />自分のデッキを上から4枚オープンできる。その中のカード名に「モスラ」と入っているスピリットカード1枚を手札に加える。残ったカードは好きな順番でデッキの下に戻す。","info_15":"［Lv2］<br />自分の緑のスピリットすべてをBP+2000する。","info_16":null,"info_17":"インドネシア諸島に存在する島。<br />島の中には遺跡があり、壁画にはモスラとバトラが描かれている。<br />－ゴジラvsモスラ（1992）－","info_18":null,"info_19":null,"info_20":null,"info_21":"とう","info_22":"はいちじ<br />じぶん うえ まい なか めい はい まい てふだ くわ のこ す じゅんばん した もど","info_23":"じぶん みどり","info_24":null,"info_25":"-","info_26":null,"info_27":"BSC19-043","info_28":"BSC19-043","info_29":null,"info_30":"-","info_31":null,"info_32":null,"info_33":null,"info_34":"-","info_35":null,"info_36":null,"info_37":null,"info_38":null,"info_39":null,"info_40":null,"info_41":"英凡島","info_42":"LV1・LV2「這張核心卡配置時」可從自己牌組上公開4張卡牌。把當中卡名中包含「モスラ」的1張靈魂卡加進手牌。餘下的卡牌放回牌組最下。<br />LV2 自己綠色的靈魂卡全部 +2000BP。\n","info_43":null,"info_44":null,"info_45":null,"info_46":null,"info_47":null,"info_48":null,"info_49":null,"info_50":null,"delflg":"0","created":"2015-03-11 15:50:55","modified":"2015-03-11 15:50:55","rank":"94257","freewords":"BSC19-043 インファント島 ネクサス 緑 ［Lv1-Lv2］『このネクサスの配置時』<br />自分のデッキを上から4枚オープンできる。その中のカード名に「モスラ」と入っているスピリットカード1枚を手札に加える。残ったカードは好きな順番でデッキの下に戻す。 ［Lv2］<br />自分の緑のスピリットすべてをBP+2000する。  とう はいちじ<br />じぶん うえ まい なか めい はい まい てふだ くわ のこ す じゅんばん した もど じぶん みどり     ","cost_icon":"<img src='../image/card_serch/icon_green.gif' /><img src='../image/card_serch/icon_green.gif' />","faq":"BSC19-043"},{"id":"94258","character_id":"62","prodid":"62065","subid":"2","info_1":"BSC19-044","info_2":"メカゴジラ格納庫","info_3":"ネクサス","info_4":"白","info_5":"4","info_6":"白2","info_7":"-","info_8":"-","info_9":"1","info_10":"-","info_11":null,"info_12":"-","info_13":"U","info_14":"［Lv1-Lv2］『このネクサスの配置時』<br />自分のデッキを上から4枚オープンできる。カード名に「メカゴジラ」か「3式機龍」と入っているスピリットカード1枚を手札に加える。残ったカードは好きな順番でデッキの下に戻す。","info_15":"［Lv2］『相手のアタックステップ』<br />自分の白のスピリットがブロックしたとき、ボイドからコア1個を自分のスピリットに置く。","info_16":null,"info_17":"戦闘のために作られた対Ｇ特殊兵器は、<br />防衛庁技術研究所に格納をされていた。<br />－ゴジラvsメカゴジラ（1993）－","info_18":null,"info_19":null,"info_20":null,"info_21":"かくのうこ","info_22":"はいちじ<br />じぶん うえ まい めい しききりゅう はい まい てふだ くわ のこ す じゅんばん した もど","info_23":"あいて<br />じぶん しろ こ じぶん お","info_24":null,"info_25":"-","info_26":null,"info_27":"BSC19-044","info_28":"BSC19-044","info_29":null,"info_30":"-","info_31":null,"info_32":null,"info_33":null,"info_34":"-","info_35":null,"info_36":null,"info_37":null,"info_38":null,"info_39":null,"info_40":null,"info_41":"機械哥斯拉格納庫","info_42":"LV1・LV2「這張核心卡配置時」可從自己牌組上公開4張卡牌。把當中卡名中包含「メカゴジラ」或「3式機龍」的1張靈魂卡加進手牌。餘下的卡牌放回牌組最下。<br />LV2「對手的攻擊階段」自己白色的靈魂卡防禦時，從空間取1個能量至自己的靈魂卡上。\n","info_43":null,"info_44":null,"info_45":null,"info_46":null,"info_47":null,"info_48":null,"info_49":null,"info_50":null,"delflg":"0","created":"2015-03-11 15:50:55","modified":"2015-03-11 15:50:55","rank":"94258","freewords":"BSC19-044 メカゴジラ格納庫 ネクサス 白 ［Lv1-Lv2］『このネクサスの配置時』<br />自分のデッキを上から4枚オープンできる。カード名に「メカゴジラ」か「3式機龍」と入っているスピリットカード1枚を手札に加える。残ったカードは好きな順番でデッキの下に戻す。 ［Lv2］『相手のアタックステップ』<br />自分の白のスピリットがブロックしたとき、ボイドからコア1個を自分のスピリットに置く。  かくのうこ はいちじ<br />じぶん うえ まい めい しききりゅう はい まい てふだ くわ のこ す じゅんばん した もど あいて<br />じぶん しろ こ じぶん お     ","cost_icon":"<img src='../image/card_serch/icon_white.gif' /><img src='../image/card_serch/icon_white.gif' />","faq":"BSC19-044"},{"id":"94259","character_id":"62","prodid":"62065","subid":"2","info_1":"BSC19-045","info_2":"Gサミット","info_3":"ネクサス","info_4":"白","info_5":"4","info_6":"白2","info_7":"-","info_8":"-","info_9":"4","info_10":"-","info_11":null,"info_12":"-","info_13":"C","info_14":"［Lv1-Lv2］『相手のアタックステップ』<br />自分の白のスピリットすべてをBP+3000する。","info_15":"［Lv2］『相手のアタックステップ開始時』<br />相手のスピリット1体を指定する。このターンの間、指定されたスピリットはアタックできない。","info_16":null,"info_17":"ゴジラの脅威から世界を解放するために設立された国連Ｇ対策センターでは、<br />ゴジラへの対策が日々研究されている。<br />－ゴジラvsデストロイア（1995）－","info_18":null,"info_19":null,"info_20":null,"info_21":"ジー","info_22":"あいて<br />じぶん しろ","info_23":"あいて かいしじ<br />あいて たい してい あいだ してい","info_24":null,"info_25":"-","info_26":null,"info_27":"BSC19-045","info_28":"BSC19-045","info_29":null,"info_30":"-","info_31":null,"info_32":null,"info_33":null,"info_34":"-","info_35":null,"info_36":null,"info_37":null,"info_38":null,"info_39":null,"info_40":null,"info_41":"G首腦會議","info_42":"LV1・LV2「對手的攻擊階段」自己全部白色的靈魂卡 +3000BP。<br />LV2「對手的攻擊階段開始時」指定對手1張靈魂卡。這回合期間，被指定的靈魂卡不能攻擊。\n","info_43":null,"info_44":null,"info_45":null,"info_46":null,"info_47":null,"info_48":null,"info_49":null,"info_50":null,"delflg":"0","created":"2015-03-11 15:50:55","modified":"2015-03-11 15:50:55","rank":"94259","freewords":"BSC19-045 Gサミット ネクサス 白 ［Lv1-Lv2］『相手のアタックステップ』<br />自分の白のスピリットすべてをBP+3000する。 ［Lv2］『相手のアタックステップ開始時』<br />相手のスピリット1体を指定する。このターンの間、指定されたスピリットはアタックできない。  ジー あいて<br />じぶん しろ あいて かいしじ<br />あいて たい してい あいだ してい     ","cost_icon":"<img src='../image/card_serch/icon_white.gif' /><img src='../image/card_serch/icon_white.gif' />","faq":"沒有"},{"id":"94260","character_id":"62","prodid":"62065","subid":"2","info_1":"BSC19-046","info_2":"引力光線","info_3":"マジック","info_4":"赤","info_5":"4","info_6":"赤2","info_7":"-","info_8":"-","info_9":null,"info_10":"-","info_11":null,"info_12":"-","info_13":"U","info_14":"［バースト：相手の『このスピリット/ブレイヴの召喚時』発揮後］<br />BP合計5000まで相手のスピリットを好きなだけ破壊する。<br />その後コストを支払うことで、このカードのメイン効果を発揮する。<br />［メイン］<br />自分のトラッシュにある赤のスピリットカード1枚を手札に戻す。","info_15":null,"info_16":null,"info_17":null,"info_18":null,"info_19":null,"info_20":null,"info_21":"いんりょくこうせん","info_22":"あいて しょうかんじ はっきご<br />ごうけい あいて す はかい<br />ご しはら こうか はっき<br />じぶん あか まい てふだ もど","info_23":null,"info_24":null,"info_25":"-","info_26":null,"info_27":"BSC19-046","info_28":"BSC19-046","info_29":null,"info_30":"-","info_31":null,"info_32":null,"info_33":null,"info_34":"-","info_35":null,"info_36":null,"info_37":null,"info_38":null,"info_39":null,"info_40":null,"info_41":"引力光線","info_42":"LV1・LV2 自己卡名中包含「モスラ」的靈魂卡被破壞時，從空間取1個能量至自己的預備區。<br />LV2「對手的攻擊階段」自己生命值被削減時，每減少1個生命值的能量，就從自己牌組抽1張牌。\n","info_43":null,"info_44":null,"info_45":null,"info_46":null,"info_47":null,"info_48":null,"info_49":null,"info_50":null,"delflg":"0","created":"2015-03-11 15:50:55","modified":"2015-03-11 15:50:55","rank":"94260","freewords":"BSC19-046 引力光線 マジック 赤 ［バースト：相手の『このスピリット/ブレイヴの召喚時』発揮後］<br />BP合計5000まで相手のスピリットを好きなだけ破壊する。<br />その後コストを支払うことで、このカードのメイン効果を発揮する。<br />［メイン］<br />自分のトラッシュにある赤のスピリットカード1枚を手札に戻す。   いんりょくこうせん あいて しょうかんじ はっきご<br />ごうけい あいて す はかい<br />ご しはら こうか はっき<br />じぶん あか まい てふだ もど      ","cost_icon":"<img src='../image/card_serch/icon_red.gif' /><img src='../image/card_serch/icon_red.gif' />","faq":"BSC19-046"},{"id":"94261","character_id":"62","prodid":"62065","subid":"2","info_1":"BSC19-047","info_2":"オキシジェン・デストロイヤー","info_3":"マジック","info_4":"赤","info_5":"7","info_6":"赤4","info_7":"-","info_8":"-","info_9":null,"info_10":"-","info_11":null,"info_12":"-","info_13":"R","info_14":null,"info_15":"［フラッシュ］<br />BP10000以下の相手のスピリット/アルティメット1体を破壊する。<br />この効果発揮後、自分のトラッシュにあるカード名に「デストロイア」と入っているスピリットカードを、好きなだけ手札に戻す。","info_16":null,"info_17":null,"info_18":null,"info_19":null,"info_20":null,"info_21":null,"info_22":null,"info_23":"いか あいて たい はかい<br />こうかはっきご じぶん めい はい す てふだ もど","info_24":null,"info_25":"-","info_26":null,"info_27":"BSC19-047","info_28":"BSC19-047","info_29":null,"info_30":"-","info_31":null,"info_32":null,"info_33":null,"info_34":"-","info_35":null,"info_36":null,"info_37":null,"info_38":null,"info_39":null,"info_40":null,"info_41":"酸素破壞者","info_42":"靈動：破壞對手1張BP10000或以下的靈魂卡/究極卡。這效果發揮後，自己廢棄區中卡名中包含「デストロイア」靈魂卡，隨喜好不限數量地回到手牌。\n","info_43":null,"info_44":null,"info_45":null,"info_46":null,"info_47":null,"info_48":null,"info_49":null,"info_50":null,"delflg":"0","created":"2015-03-11 15:50:55","modified":"2015-03-11 15:50:55","rank":"94261","freewords":"BSC19-047 オキシジェン・デストロイヤー マジック 赤  ［フラッシュ］<br />BP10000以下の相手のスピリット/アルティメット1体を破壊する。<br />この効果発揮後、自分のトラッシュにあるカード名に「デストロイア」と入っているスピリットカードを、好きなだけ手札に戻す。    いか あいて たい はかい<br />こうかはっきご じぶん めい はい す てふだ もど     ","cost_icon":"<img src='../image/card_serch/icon_red.gif' /><img src='../image/card_serch/icon_red.gif' /><img src='../image/card_serch/icon_red.gif' /><img src='../image/card_serch/icon_red.gif' />","faq":"BSC19-047"},{"id":"94262","character_id":"62","prodid":"62065","subid":"2","info_1":"BSC19-048","info_2":"モスラの羽化","info_3":"マジック","info_4":"緑","info_5":"3","info_6":"緑2","info_7":"-","info_8":"-","info_9":null,"info_10":"-","info_11":null,"info_12":"-","info_13":"R","info_14":null,"info_15":"［フラッシュ］<br />相手のスピリット1体を疲労させる。<br />自分のライフが2以下のとき、さらに、自分の手札にあるカード名に「モスラ」と入っているスピリットカード1枚を、コストを支払わずに召喚できる。","info_16":null,"info_17":null,"info_18":null,"info_19":null,"info_20":null,"info_21":"うか","info_22":null,"info_23":"あいて たい ひろう <br />じぶん いか じぶん てふだ めい はい まい しはら しょうかん","info_24":null,"info_25":"-","info_26":null,"info_27":"BSC19-048","info_28":"BSC19-048","info_29":null,"info_30":"-","info_31":null,"info_32":null,"info_33":null,"info_34":"-","info_35":null,"info_36":null,"info_37":null,"info_38":null,"info_39":null,"info_40":null,"info_41":"莫斯拉羽化","info_42":"靈動：對手1張靈魂卡變成疲勞狀態。自己生命值2個或以下時，自己手牌中1張卡名中包含「モスラ」的靈魂卡可無需支付需求召喚到場中。\n","info_43":null,"info_44":null,"info_45":null,"info_46":null,"info_47":null,"info_48":null,"info_49":null,"info_50":null,"delflg":"0","created":"2015-03-11 15:50:55","modified":"2015-03-11 15:50:55","rank":"94262","freewords":"BSC19-048 モスラの羽化 マジック 緑  ［フラッシュ］<br />相手のスピリット1体を疲労させる。<br />自分のライフが2以下のとき、さらに、自分の手札にあるカード名に「モスラ」と入っているスピリットカード1枚を、コストを支払わずに召喚できる。  うか  あいて たい ひろう <br />じぶん いか じぶん てふだ めい はい まい しはら しょうかん     ","cost_icon":"<img src='../image/card_serch/icon_green.gif' /><img src='../image/card_serch/icon_green.gif' />","faq":"BSC19-048"},{"id":"94263","character_id":"62","prodid":"62065","subid":"2","info_1":"BSC19-049","info_2":"モスラの歌","info_3":"マジック","info_4":"緑","info_5":"4","info_6":"緑2","info_7":"-","info_8":"-","info_9":null,"info_10":"-","info_11":null,"info_12":"-","info_13":"U","info_14":"［バースト：相手による自分のスピリット破壊後］<br />ボイドからコア1個を自分のスピリットに置く。<br />その後コストを支払うことで、このカードのフラッシュ効果を発揮する。","info_15":"［フラッシュ］<br />自分の緑のスピリット1体を回復させる。<br />この効果でカード名に「モスラ」と入っているスピリットが回復したとき、相手のスピリット1体を疲労させる。","info_16":null,"info_17":null,"info_18":null,"info_19":null,"info_20":null,"info_21":"うた","info_22":"あいて じぶん はかいご<br />こ じぶん お<br />ご しはら こうか はっき","info_23":"じぶん みどり たい かいふく <br />こうか めい はい かいふく あいて たい ひろう","info_24":null,"info_25":"-","info_26":null,"info_27":"BSC19-049","info_28":"BSC19-049","info_29":null,"info_30":"-","info_31":null,"info_32":null,"info_33":null,"info_34":"-","info_35":null,"info_36":null,"info_37":null,"info_38":null,"info_39":null,"info_40":null,"info_41":"莫斯拉之歌","info_42":"【Burst：自己的靈魂卡被對手破壞後】從空間取1個能量至自己的靈魂卡上。然後支付需求，發揮這張卡牌的靈動效果。<br />靈動：自己1張綠色靈魂卡變成回復狀態。卡名中包含「モスラ」的靈魂卡因這效果回復時，對手1張靈魂卡變成疲勞狀態。\n","info_43":null,"info_44":null,"info_45":null,"info_46":null,"info_47":null,"info_48":null,"info_49":null,"info_50":null,"delflg":"0","created":"2015-03-11 15:50:55","modified":"2015-03-11 15:50:55","rank":"94263","freewords":"BSC19-049 モスラの歌 マジック 緑 ［バースト：相手による自分のスピリット破壊後］<br />ボイドからコア1個を自分のスピリットに置く。<br />その後コストを支払うことで、このカードのフラッシュ効果を発揮する。 ［フラッシュ］<br />自分の緑のスピリット1体を回復させる。<br />この効果でカード名に「モスラ」と入っているスピリットが回復したとき、相手のスピリット1体を疲労させる。  うた あいて じぶん はかいご<br />こ じぶん お<br />ご しはら こうか はっき じぶん みどり たい かいふく <br />こうか めい はい かいふく あいて たい ひろう     ","cost_icon":"<img src='../image/card_serch/icon_green.gif' /><img src='../image/card_serch/icon_green.gif' />","faq":"BSC19-049"},{"id":"94264","character_id":"62","prodid":"62065","subid":"2","info_1":"BSC19-050","info_2":"新都心崩壊","info_3":"マジック","info_4":"白","info_5":"4","info_6":"白2","info_7":"-","info_8":"-","info_9":null,"info_10":"-","info_11":null,"info_12":"-","info_13":"U","info_14":"［バースト：自分のライフ減少後］<br />カード名に「キングギドラ」と入っている自分のスピリット1体を回復させる。<br />その後コストを支払うことで、このカードのフラッシュ効果を発揮する。","info_15":"［フラッシュ］<br />このバトルが終了したとき、アタックステップを終了する。","info_16":null,"info_17":null,"info_18":null,"info_19":null,"info_20":null,"info_21":"しんとしんほうかい","info_22":"じぶん げんしょうご<br />めい はい じぶん たい かいふく<br />ご しはら こうか はっき","info_23":"しゅうりょう しゅうりょう","info_24":null,"info_25":"-","info_26":null,"info_27":"BSC19-050","info_28":"BSC19-050","info_29":null,"info_30":"-","info_31":null,"info_32":null,"info_33":null,"info_34":"-","info_35":null,"info_36":null,"info_37":null,"info_38":null,"info_39":null,"info_40":null,"info_41":"新都心崩壞","info_42":"【Burst：自己生命值減少後】自己1張卡名中包含「キングギドラ」變成回復狀態。然後支付需求，發揮這張卡牌的靈動效果。<br />靈動：這戰鬥結束時，攻擊階段結束。\n","info_43":null,"info_44":null,"info_45":null,"info_46":null,"info_47":null,"info_48":null,"info_49":null,"info_50":null,"delflg":"0","created":"2015-03-11 15:50:55","modified":"2015-03-11 15:50:55","rank":"94264","freewords":"BSC19-050 新都心崩壊 マジック 白 ［バースト：自分のライフ減少後］<br />カード名に「キングギドラ」と入っている自分のスピリット1体を回復させる。<br />その後コストを支払うことで、このカードのフラッシュ効果を発揮する。 ［フラッシュ］<br />このバトルが終了したとき、アタックステップを終了する。  しんとしんほうかい じぶん げんしょうご<br />めい はい じぶん たい かいふく<br />ご しはら こうか はっき しゅうりょう しゅうりょう     ","cost_icon":"<img src='../image/card_serch/icon_white.gif' /><img src='../image/card_serch/icon_white.gif' />","faq":"BSC19-050"},{"id":"94265","character_id":"62","prodid":"62065","subid":"2","info_1":"BSC19-051","info_2":"3式絶対零度砲","info_3":"マジック","info_4":"白","info_5":"4","info_6":"白2","info_7":"-","info_8":"-","info_9":null,"info_10":"-","info_11":null,"info_12":"-","info_13":"R","info_14":null,"info_15":"［フラッシュ］<br />相手のスピリット1体を手札に戻す。<br />カード名に「3式機龍」か「メカゴジラ」と入っている自分のスピリットがいるとき、かわりに、相手のスピリット/アルティメット1体を手札に戻す。","info_16":null,"info_17":null,"info_18":null,"info_19":null,"info_20":null,"info_21":"アブソリュート・ゼロ","info_22":null,"info_23":"あいて たい てふだ もど<br />めい しききりゅう はい じぶん あいて たい てふだ もど","info_24":null,"info_25":"-","info_26":null,"info_27":"BSC19-051","info_28":"BSC19-051","info_29":null,"info_30":"-","info_31":null,"info_32":null,"info_33":null,"info_34":"-","info_35":null,"info_36":null,"info_37":null,"info_38":null,"info_39":null,"info_40":null,"info_41":"3式絕對零度砲","info_42":"靈動：對手1張靈魂卡回到手牌。自己有卡名中包含「3式機龍」或「メカゴジラ」的靈魂卡時，改為對手1張靈魂卡/究極卡回到手牌。\n","info_43":null,"info_44":null,"info_45":null,"info_46":null,"info_47":null,"info_48":null,"info_49":null,"info_50":null,"delflg":"0","created":"2015-03-11 15:50:55","modified":"2015-03-11 15:50:55","rank":"94265","freewords":"BSC19-051 3式絶対零度砲 マジック 白  ［フラッシュ］<br />相手のスピリット1体を手札に戻す。<br />カード名に「3式機龍」か「メカゴジラ」と入っている自分のスピリットがいるとき、かわりに、相手のスピリット/アルティメット1体を手札に戻す。  アブソリュート・ゼロ  あいて たい てふだ もど<br />めい しききりゅう はい じぶん あいて たい てふだ もど     ","cost_icon":"<img src='../image/card_serch/icon_white.gif' /><img src='../image/card_serch/icon_white.gif' />","faq":"沒有"},{"id":"94266","character_id":"62","prodid":"62065","subid":"2","info_1":"BSC19-052","info_2":"全武装攻撃","info_3":"マジック","info_4":"白","info_5":"5","info_6":"白3","info_7":"-","info_8":"-","info_9":null,"info_10":"-","info_11":null,"info_12":"-","info_13":"R","info_14":null,"info_15":"［フラッシュ］<br />自分の白のスピリット1体を回復させる。<br />その後、カード名に「3式機龍」か「メカゴジラ」と入っている自分のスピリットすべてを回復させる。","info_16":null,"info_17":null,"info_18":null,"info_19":null,"info_20":null,"info_21":"ぜんぶそうこうげき","info_22":null,"info_23":"じぶん しろ たい かいふく<br />ご めい しききりゅう はい じぶん かいふく","info_24":null,"info_25":"-","info_26":null,"info_27":"BSC19-052","info_28":"BSC19-052","info_29":null,"info_30":"-","info_31":null,"info_32":null,"info_33":null,"info_34":"-","info_35":null,"info_36":null,"info_37":null,"info_38":null,"info_39":null,"info_40":null,"info_41":"全武裝攻擊","info_42":"靈動：自己1張白色的靈魂卡變成回復狀態。然後自己全部卡名中包含「3式機龍」或「メカゴジラ」的靈魂卡變成回復狀態。\n","info_43":null,"info_44":null,"info_45":null,"info_46":null,"info_47":null,"info_48":null,"info_49":null,"info_50":null,"delflg":"0","created":"2015-03-11 15:50:55","modified":"2015-03-11 15:50:55","rank":"94266","freewords":"BSC19-052 全武装攻撃 マジック 白  ［フラッシュ］<br />自分の白のスピリット1体を回復させる。<br />その後、カード名に「3式機龍」か「メカゴジラ」と入っている自分のスピリットすべてを回復させる。  ぜんぶそうこうげき  じぶん しろ たい かいふく<br />ご めい しききりゅう はい じぶん かいふく     ","cost_icon":"<img src='../image/card_serch/icon_white.gif' /><img src='../image/card_serch/icon_white.gif' /><img src='../image/card_serch/icon_white.gif' />","faq":"沒有"},{"id":"94248","character_id":"62","prodid":"62065","subid":"2","info_1":"BSC19-X01","info_2":"キングギドラ［1991］","info_3":"スピリット","info_4":"赤","info_5":"7","info_6":"赤3青1","info_7":"1","info_8":"5000","info_9":"2","info_10":"10000","info_11":"4","info_12":"13000","info_13":"X","info_14":"［Lv1-Lv2-Lv3］『このスピリットの召喚時』<br />BP7000以下の相手のスピリット/アルティメット3体を破壊する。","info_15":"［Lv2-Lv3］【強襲：2】『このスピリットのアタック時』<br />このスピリットは、ターンに2回まで、自分のネクサス1つを疲労させることで回復できる。","info_16":null,"info_17":"未来人の謀略によって作り出された怪獣。<br />金色のボディにコウモリの羽根、3本の龍の首を持ち引力光線で、<br />あらゆる物を破壊する。　－ゴジラvsキングギドラ（1991）－","info_18":null,"info_19":null,"info_20":null,"info_21":null,"info_22":"しょうかんじ<br />いか あいて たい はかい","info_23":"きょうしゅう じ<br />かい じぶん ひろう かいふく","info_24":null,"info_25":"星竜・海首","info_26":"せいりゅう　かいしゅ","info_27":"BSC19-X01","info_28":"BSC19-X01","info_29":null,"info_30":"-","info_31":null,"info_32":null,"info_33":null,"info_34":"-","info_35":null,"info_36":null,"info_37":null,"info_38":null,"info_39":null,"info_40":null,"info_41":"王者基多拉[1991]","info_42":"LV1・LV2・LV3「這張靈魂卡召喚時」破壞對手3張BP7000或以下的靈魂卡/究極卡。<br />LV2・LV3【強襲：2】「這張靈魂卡攻擊時」這張靈魂卡每回合最多2次，可在疲勞自己1張核心卡後，變成回復狀態。\n","info_43":null,"info_44":null,"info_45":null,"info_46":null,"info_47":null,"info_48":null,"info_49":null,"info_50":null,"delflg":"0","created":"2015-03-11 15:50:55","modified":"2015-03-11 15:50:55","rank":"94248","freewords":"BSC19-X01 キングギドラ［1991］ スピリット 赤 ［Lv1-Lv2-Lv3］『このスピリットの召喚時』<br />BP7000以下の相手のスピリット/アルティメット3体を破壊する。 ［Lv2-Lv3］【強襲：2】『このスピリットのアタック時』<br />このスピリットは、ターンに2回まで、自分のネクサス1つを疲労させることで回復できる。   しょうかんじ<br />いか あいて たい はかい きょうしゅう じ<br />かい じぶん ひろう かいふく  星竜・海首 せいりゅう　かいしゅ  ","cost_icon":"<img src='../image/card_serch/icon_red.gif' /><img src='../image/card_serch/icon_red.gif' /><img src='../image/card_serch/icon_red.gif' /><img src='../image/card_serch/icon_blue.gif' />","faq":"BSC19-X01"},{"id":"94249","character_id":"62","prodid":"62065","subid":"2","info_1":"BSC19-X02","info_2":"スペースゴジラ","info_3":"スピリット","info_4":"赤","info_5":"8","info_6":"赤4","info_7":"1","info_8":"7000","info_9":"3","info_10":"12000","info_11":"4","info_12":"14000","info_13":"X","info_14":"［Lv1-Lv2-Lv3］『このスピリットのアタック時』<br />BP10000以下の相手のスピリット/アルティメット1体を破壊し、自分はデッキから1枚ドローする。","info_15":"［Lv2-Lv3］『このスピリットのアタック時』<br />自分はデッキから1枚ドローする。その後、自分の手札1枚につき、このスピリットをBP+2000する。","info_16":"［Lv3］<br />自分の[結晶地帯]すべてをLv2として扱う。","info_17":"宇宙に飛び立ったG細胞がブラックホールの異常な時間の流れで進化を遂げ、<br />結晶体生命体を取り込み恒星爆発のエネルギーを浴びて誕生した宇宙怪獣。<br />－ゴジラvsスペースゴジラ（1994）－","info_18":null,"info_19":null,"info_20":null,"info_21":null,"info_22":"じ<br />いか あいて たい はかい じぶん まい","info_23":"じ<br />じぶん まい ご じぶん てふだ まい","info_24":"じぶん けっしょうちたい あつか","info_25":"星竜","info_26":"せいりゅう","info_27":"BSC19-X02","info_28":"BSC19-X02","info_29":null,"info_30":"-","info_31":null,"info_32":null,"info_33":null,"info_34":"-","info_35":null,"info_36":null,"info_37":null,"info_38":null,"info_39":null,"info_40":null,"info_41":"太空哥斯拉","info_42":"LV1・LV2・LV3「這張靈魂卡攻擊時」破壞對手1張BP10000或以下的靈魂卡/究極卡，從自己牌組抽取1張卡牌。<br />LV2・LV3「這張靈魂卡攻擊時」從自己牌組抽取1張卡牌。然後，自己每有1張手牌，這張靈魂卡就+2000BP。<br />LV3 自己全部[結晶地帯]當作LV2使用。\n","info_43":null,"info_44":null,"info_45":null,"info_46":null,"info_47":null,"info_48":null,"info_49":null,"info_50":null,"delflg":"0","created":"2015-03-11 15:50:55","modified":"2015-03-11 15:50:55","rank":"94249","freewords":"BSC19-X02 スペースゴジラ スピリット 赤 ［Lv1-Lv2-Lv3］『このスピリットのアタック時』<br />BP10000以下の相手のスピリット/アルティメット1体を破壊し、自分はデッキから1枚ドローする。 ［Lv2-Lv3］『このスピリットのアタック時』<br />自分はデッキから1枚ドローする。その後、自分の手札1枚につき、このスピリットをBP+2000する。 ［Lv3］<br />自分の[結晶地帯]すべてをLv2として扱う。  じ<br />いか あいて たい はかい じぶん まい じ<br />じぶん まい ご じぶん てふだ まい じぶん けっしょうちたい あつか 星竜 せいりゅう  ","cost_icon":"<img src='../image/card_serch/icon_red.gif' /><img src='../image/card_serch/icon_red.gif' /><img src='../image/card_serch/icon_red.gif' /><img src='../image/card_serch/icon_red.gif' />","faq":"BSC19-X02"},{"id":"94250","character_id":"62","prodid":"62065","subid":"2","info_1":"BSC19-X03","info_2":"デストロイア（完全体）","info_3":"スピリット","info_4":"赤・紫","info_5":"10","info_6":"赤5紫1","info_7":"1","info_8":"8000","info_9":"3","info_10":"15000","info_11":"5","info_12":"20000","info_13":"X","info_14":"［Lv1-Lv2-Lv3］『このスピリットの破壊時』<br />自分のトラッシュにあるカード名に「デストロイア」と入っているスピリットカードを、コストを支払わずに好きなだけ召喚する。","info_15":"［Lv2-Lv3：フラッシュ］『このスピリットのアタック時』<br />疲労状態の相手のスピリット1体を破壊することで、このスピリットを破壊する。","info_16":null,"info_17":"増殖・合体を繰り返しながら進化を繰り返したデストロイアの完全形態。<br />－ゴジラvsデストロイア（1995）－","info_18":null,"info_19":null,"info_20":null,"info_21":"かんぜんたい","info_22":"はかいじ<br />じぶん めい はい しはら す しょうかん","info_23":"じ<br />ひろうじょうたい あいて たい はかい はかい","info_24":null,"info_25":"滅龍","info_26":"めつりゅう","info_27":"BSC19-X03","info_28":"BSC19-X03","info_29":null,"info_30":"-","info_31":null,"info_32":null,"info_33":null,"info_34":"-","info_35":null,"info_36":null,"info_37":null,"info_38":null,"info_39":null,"info_40":null,"info_41":"戴斯特洛伊亞(完全體)","info_42":"LV1・LV2・LV3「這張靈魂卡被破壞時」自己廢棄區中卡名中包含「デストロイア」的靈魂卡，無需支付需求隨喜好不限數量地召喚到場中。<br />LV2・LV3：靈動「這張靈魂卡攻擊時」只要破壞對手1張處於疲勞狀態的靈魂卡，這張靈魂卡就會被破壞。\n","info_43":null,"info_44":null,"info_45":null,"info_46":null,"info_47":null,"info_48":null,"info_49":null,"info_50":null,"delflg":"0","created":"2015-03-11 15:50:55","modified":"2015-03-11 15:50:55","rank":"94250","freewords":"BSC19-X03 デストロイア（完全体） スピリット 赤・紫 ［Lv1-Lv2-Lv3］『このスピリットの破壊時』<br />自分のトラッシュにあるカード名に「デストロイア」と入っているスピリットカードを、コストを支払わずに好きなだけ召喚する。 ［Lv2-Lv3：フラッシュ］『このスピリットのアタック時』<br />疲労状態の相手のスピリット1体を破壊することで、このスピリットを破壊する。  かんぜんたい はかいじ<br />じぶん めい はい しはら す しょうかん じ<br />ひろうじょうたい あいて たい はかい はかい  滅龍 めつりゅう  ","cost_icon":"<img src='../image/card_serch/icon_red.gif' /><img src='../image/card_serch/icon_red.gif' /><img src='../image/card_serch/icon_red.gif' /><img src='../image/card_serch/icon_red.gif' /><img src='../image/card_serch/icon_red.gif' /><img src='../image/card_serch/icon_pup.gif' />","faq":"BSC19-X03"},{"id":"94251","character_id":"62","prodid":"62065","subid":"2","info_1":"BSC19-X04","info_2":"モスラ［1992］","info_3":"スピリット","info_4":"緑","info_5":"8","info_6":"緑4","info_7":"1","info_8":"6000","info_9":"3","info_10":"10000","info_11":null,"info_12":"-","info_13":"X","info_14":"［Lv1-Lv2］『このスピリットの召喚時』<br />相手のスピリット2体を疲労させ、ボイドからコア2個をこのスピリットに置く。","info_15":"［Lv2］『相手によるこのスピリットの破壊時』<br />相手のスピリット/アルティメット2体を疲労させ、このスピリットは手札に戻る。","info_16":null,"info_17":"傷ついたモスラの幼虫が国会議事堂に繭を作り、最終決戦に臨むべく変化した姿。<br />触角から超音波ビームを発射する。<br />－ゴジラvsモスラ（1992）－","info_18":null,"info_19":null,"info_20":null,"info_21":null,"info_22":"しょうかんじ<br />あいて たい ひろう こ お","info_23":"あいて はかいじ<br />あいて たい ひろう てふだ もど","info_24":null,"info_25":"怪虫","info_26":"かいちゅう","info_27":"BSC19-X04","info_28":"BSC19-X04","info_29":null,"info_30":"-","info_31":null,"info_32":null,"info_33":null,"info_34":"-","info_35":null,"info_36":null,"info_37":null,"info_38":null,"info_39":null,"info_40":null,"info_41":"莫斯拉[1992]","info_42":"LV1・LV2「這張靈魂卡召喚時」對手2張靈魂卡變成疲勞狀態，從空間取2個能量至這張靈魂卡上。<br />LV2「這張靈魂卡被對手破壞時」對手2張靈魂卡/究極卡變成疲勞狀態，這張靈魂卡回到手牌。\n","info_43":null,"info_44":null,"info_45":null,"info_46":null,"info_47":null,"info_48":null,"info_49":null,"info_50":null,"delflg":"0","created":"2015-03-11 15:50:55","modified":"2015-03-11 15:50:55","rank":"94251","freewords":"BSC19-X04 モスラ［1992］ スピリット 緑 ［Lv1-Lv2］『このスピリットの召喚時』<br />相手のスピリット2体を疲労させ、ボイドからコア2個をこのスピリットに置く。 ［Lv2］『相手によるこのスピリットの破壊時』<br />相手のスピリット/アルティメット2体を疲労させ、このスピリットは手札に戻る。   しょうかんじ<br />あいて たい ひろう こ お あいて はかいじ<br />あいて たい ひろう てふだ もど  怪虫 かいちゅう  ","cost_icon":"<img src='../image/card_serch/icon_green.gif' /><img src='../image/card_serch/icon_green.gif' /><img src='../image/card_serch/icon_green.gif' /><img src='../image/card_serch/icon_green.gif' />","faq":"沒有"},{"id":"94252","character_id":"62","prodid":"62065","subid":"2","info_1":"BSC19-X05","info_2":"3式機龍〈改〉","info_3":"スピリット","info_4":"白","info_5":"8","info_6":"白4","info_7":"1","info_8":"7000","info_9":"2","info_10":"11000","info_11":"4","info_12":"14000","info_13":"X","info_14":"［Lv1-Lv2-Lv3］【超装甲：赤/緑/白】<br />このスピリットは、相手の赤/緑/白のスピリット/アルティメット/ネクサス/マジックの効果を受けない。<br />［Lv1-Lv2-Lv3］『このスピリットのアタック時』<br />このスピリットのBP以下の相手のスピリット/アルティメット1体を手札に戻す。","info_15":null,"info_16":"［Lv3］『相手によるこのスピリットの破壊時』<br />相手のスピリット/アルティメット1体をデッキの下に戻す。","info_17":"3式機龍を改修した機体。右手をドリルに換装し、<br />胸部には4式3連装ハイパーメーサー砲を装備している。<br />－ゴジラ×モスラ×メカゴジラ　東京ＳＯＳ（2003）－","info_18":null,"info_19":null,"info_20":null,"info_21":"しききりゅう かい","info_22":"ちょうそうこう あか みどり しろ<br />あいて あか みどり しろ こうか う<br />じ<br />いか あいて　たい てふだ もど","info_23":null,"info_24":"あいて はかいじ<br />あいて たい した もど","info_25":"機獣","info_26":"きじゅう","info_27":"BSC19-X05","info_28":"BSC19-X05","info_29":null,"info_30":"-","info_31":null,"info_32":null,"info_33":null,"info_34":"-","info_35":null,"info_36":null,"info_37":null,"info_38":null,"info_39":null,"info_40":null,"info_41":"3式機龍〈改〉","info_42":"LV1・LV2・LV3【超裝甲：紅/綠/白】這張靈魂卡/究極卡不受對手紅/綠/白色的靈魂卡/究極卡/核心卡/魔法卡效果影響。<br />LV1・LV2・LV3「這張靈魂卡攻擊時」對手1張BP比這張靈魂卡低，或相同的靈魂卡/究極卡回到手牌。<br />LV3「這張靈魂卡被對手破壞時」對手1張靈魂卡/究極卡回到牌組最下。\n","info_43":null,"info_44":null,"info_45":null,"info_46":null,"info_47":null,"info_48":null,"info_49":null,"info_50":null,"delflg":"0","created":"2015-03-11 15:50:55","modified":"2015-03-11 15:50:55","rank":"94252","freewords":"BSC19-X05 3式機龍〈改〉 スピリット 白 ［Lv1-Lv2-Lv3］【超装甲：赤/緑/白】<br />このスピリットは、相手の赤/緑/白のスピリット/アルティメット/ネクサス/マジックの効果を受けない。<br />［Lv1-Lv2-Lv3］『このスピリットのアタック時』<br />このスピリットのBP以下の相手のスピリット/アルティメット1体を手札に戻す。  ［Lv3］『相手によるこのスピリットの破壊時』<br />相手のスピリット/アルティメット1体をデッキの下に戻す。 しききりゅう かい ちょうそうこう あか みどり しろ<br />あいて あか みどり しろ こうか う<br />じ<br />いか あいて　たい てふだ もど  あいて はかいじ<br />あいて たい した もど 機獣 きじゅう  ","cost_icon":"<img src='../image/card_serch/icon_white.gif' /><img src='../image/card_serch/icon_white.gif' /><img src='../image/card_serch/icon_white.gif' /><img src='../image/card_serch/icon_white.gif' />","faq":"BSC19-X05"}]}